Workbook

Sheet README
A1: EU4+UK Angelman Syndrome Treatment Centres and KOLs — Mapping & Tiering
A3: SCOPE
A4: Title | B4: EU4+UK Angelman Syndrome Treatment Centres and KOLs — Mapping & Tiering
A5: Prepared for | B5: Medical Affairs workstream — obudanersen (ION582, Ionis) (Angelman syndrome)
A6: Geographies | B6: Germany, France, Italy, Spain, United Kingdom (EU4+UK)
A7: Asset phase | B7: Pre-approval (Phase 3 REVEAL NCT06914609 fully enrolled; topline 2H 2027)
A8: Date compiled | B8: 46309
A9: Compiled by | B9: Copilot Cowork (automated, high-effort run) for Ian Pepper
A10: Method | B10: Cross-referenced from public sources (ClinicalTrials.gov / EU CTIS, ERN ITHACA / EpiCARE HCP lists, national guidelines, national AS patient organisations, Orphanet, sponsor communications, PubMed / publisher records). Template: PROMPT_KOL_Centre_Map_v2.
A11: Content | B11: 95 centres (Tiers 1–3) · 97 named KOLs · 150 sources · 92 verification items
A13: TAB GUIDE
A14: README | B14: Scope, five signal pillars, Centre and KOL tier definitions + scoring criteria, critical caveats, asset overlay & facts, gap-fill methodology, how to use.
A15: Country_Centres | B15: Master flat table — one row per Tier 1–3 centre; P1–P5 signal flags; notes with source URLs. Sorted by Country then Tier; autofilter on.
A16: KOL_Roster | B16: Named clinicians/scientists with role, P1/P3 roles, P2 publications, international presentations, engagement priority, the seven KOL scores, formula Total and formula KOL Tier for TOV, plus sources.
A17: Tier_Counts | B17: Centre and KOL country × tier matrices with interpretive notes, plus cross-cut counts — all live COUNTIFS/SUMPRODUCT formulas on the data tabs.
A18: Infrastructure | B18: AS diagnostic, severity-assessment, treatment, chronic-management and future-state (obudanersen IT-ASO) requirements mapped to Tier 1–2 coverage.
A19: Sources_Caveats | B19: Authoritative sources with clickable URLs; caveats (all-geography + per-country); asset & competitor trial footprint (competitor programmes; EU4+UK trial sites).
A20: Verification_Flags | B20: Adversarial QA pass — affiliation currency, independence/compliance, provenance, wording/counts, drug premise; flagged source cells highlighted red on their home sheets (not auto-corrected).
A22: THE FIVE SIGNAL PILLARS (calibrated for Angelman syndrome)
A23: P1 — Consensus 2022 / national guideline author | B23: Guideline authorship — Duis et al. 2022 international consensus standards of care (Mol Genet Genomic Med 10:e1843; doi:10.1002/mgg3.1843; PMID 35150089) plus national guidance: France PNDS Syndrome d'Angelman (CRMR Déficiences intellectuelles de causes rares, HAS, Dec-2021); diagnostic anchor Williams 2006 criteria (PMID 16470747). No national AS guideline identified for DE/IT/ES/UK — country-level P1 relies on consensus authorship.
A24: P2 — AS publications / ION582 or competitor trial (5y) | B24: Publication & trial authorship — AS peer-reviewed output 2021–2026 and investigator roles on obudanersen HALOS (NCT05127226)/REVEAL (NCT06914609)/CHAMPION (NCT07782827) and competitor programmes: apazunersen Ph1/2 (NCT04259281) & Aspire (NCT06617429; failed Sep-2026), rugonersen TANGELO (NCT04428281; Nat Med 2025), gaboxadol NEPTUNE (NCT04106557; PMID 37639777).
A25: P3 — AS registry / trial-network coord/site | B25: Registry / trial-network participation — Global Angelman Syndrome Registry (angelmanregistry.info), LADDER via the ASF International Clinic Network (Erasmus MC partner, Jan-2026), national registries (e.g. Italian RISA/FROM), and REVEAL/HALOS/Aspire/TANGELO site networks per ClinicalTrials.gov.
A26: P4 — ERN ITHACA / EpiCARE HCP | B26: Reference-network membership — ERN ITHACA HCP (primary) and ERN EpiCARE HCP (secondary), per EC ERN Service Directory; UK = N/A (post-Brexit) with NHS highly specialised/regional genetics services as analogue; national analogues FR CRMR/CCMR (DéfiScience/AnDDI-Rares), ES CSUR, DE ZSE, IT regional rare-disease networks.
A27: P5 — Angelman clinic / programme | B27: Disease programme — named multidisciplinary Angelman clinic (Yes) or broader ID/neurogenetics/rare-epilepsy programme (Partial), sourced from national patient organisations (Angelman e.V., AFSA, OR.S.A., ASA, AngelmanUK/FAST UK) and hospital pages.
A29: CENTRE TIER DEFINITIONS (template §3)
A30: Tier 1 — Anchor / reference | B30: Definition: hosts a P1 guideline author OR a P3 registry coordinator, AND is a P4 reference-network HCP (or its national equivalent), AND carries the P2 publication signal (disease- or asset-/competitor-trial authorship in the last ~5 years). Role in plan: first-wave KOL engagement; advisory-board core; RWE and observational lead candidates; the asset's likely evidence partners.
A31: Tier 2 — National referral | B31: Definition: a P4 HCP with the relevant P5 programme, OR a P3 participating site; university hospital with full critical/specialist care and disease-relevant diagnostics; recurring P2 authorship on the relevant literature. Role in plan: second-wave outreach; regional referral hubs.
A32: Tier 3 — Tertiary capable | B32: Definition: national/regional reference centre or large university hospital with the core treatment infrastructure but typically not research-active in the disease. Role in plan: launch-phase distribution; HCP education; not advisory core.
A33: Tier 4 — Community / acute presentation | B33: Definition: district/general hospitals where patients first present and receive supportive care, then refer on. Role in plan: enumerate only if explicitly asked (too dispersed) — NOT enumerated in this build (not requested). Matters for case-finding, patient pathway and pharmacovigilance — address via national-society / patient-organisation channels, not individual outreach.
A34: Calibration note | B34: Angelman syndrome is a chronic, managed disease: care concentrates at reference / genetics / neuropaediatric centres, so the acute-presentation dispersion caveat is omitted.
A36: KOL TIER DEFINITIONS & SCORING CRITERIA (template §3)
A37: Purpose | B37: Evaluate and classify each identified physician (KOL) by level of expertise, influence and contribution to the therapeutic area.
A38: Step 1 — Guideline authorship | B38: 1 point — contributor to local protocols or internal standards; co-author of minor/regional guidelines 3 points — lead/co-author of national guidelines; contributor to multicentre consensus statements 5 points — lead/co-author of international or globally influential guidelines
A39: Step 1 — Publications | B39: 1 point — ≥3 publications (any authorship) in relevant peer-reviewed journals 3 points — ≥5 publications in reputable journals (last 7 years) 5 points — ≥5 publications as first/last author (last 7 years)
A40: Step 1 — Clinical trials | B40: 1 point — participant or site investigator in local/national trials 3 points — national PI or investigator in multi-country/regional trials (last 7 years) 5 points — lead/site PI in large international or pivotal trials influencing practice/regulation
A41: Step 1 — Academic appointment | B41: 1 point — specialist physician; working/research group member; completed specialist training 3 points — senior physician; associate professor; research group member; retired department head 5 points — department head; research group leader; emeritus professor
A42: Step 1 — Society roles | B42: 1 point — member of local/regional society 3 points — committee/board member in national society 5 points — executive leadership in major national/international societies
A43: Step 1 — Speaker engagement | B43: 1 point — occasional local/regional speaker 3 points — regular invited speaker at national conferences 5 points — keynote/plenary speaker at major international congresses
A44: Step 1 — Awards | B44: 1–2 points depending on calibre of award (0 if none evidenced)
A45: Step 2 — Scoring rules | B45: Evaluate each physician independently across all categories; assign 1, 3 or 5 points per category on best fit; use the highest level fully supported by evidence; do not infer or assume achievements; if information is limited assign the lowest reasonable score (default 1); prioritise recent (last 5–7 years) and verifiable contributions.
A46: Step 3 — Total score | B46: Sum all category scores → total score per KOL (KOL_Roster "Total score" = SUM formula of the seven score cells).
A47: Step 4 — Tier 1 (Top KOLs) | B47: 24–30 points
A48: Step 4 — Tier 2 (Established KOLs) | B48: 12–23 points
... A51: Engagement priority | B51: Ties tier to intent: "TIER 1 — must-engage", "TIER 1 — must-engage (ION582-specific)" for the asset's own evidence partners, "TIER 2 — engage", "TIER 2 — high value", "TIER 3 — monitor", plus qualifiers (— verify current lead, — national anchor, — competitor-trial PI, etc.). Engagement priority may sit above the score tier where an ION582 site role justifies it.
A53: CRITICAL CAVEATS
A54: Caveat 1 | B54: Class risk: Ultragenyx's same-mechanism UBE3A-ATS ASO apazunersen failed Phase 3 Aspire (2-Sep-2026); obudanersen efficacy evidence remains open-label, company-reported HALOS data until REVEAL topline (2H-2027).
A55: Caveat 2 | B55: Site-level PIs are not published on ClinicalTrials.gov for REVEAL, HALOS, Aspire or GTX-102 Ph1/2; investigator attribution relies on press releases, community letters and publication authorship — verify via EU CTIS/sponsor before outreach.
A56: Caveat 3 | B56: Infrastructure gate: obudanersen requires lifelong quarterly intrathecal LP under sedation/GA in a non-verbal, behaviourally complex population; adult (≥18 y) LP/sedation capacity is the scarcest resource and only some REVEAL sites certified for adult Cohort 2.
A57: Caveat 4 | B57: Genotype gating: REVEAL covers deletion + UBE3A mutation only; UPD/ID patients are addressed only by CHAMPION (open-label, US-only to date) — centre readiness needs genotype documentation/re-testing capacity.
A58: Caveat 5 | B58: Geography: France has no REVEAL site (HALOS Necker only); UK is outside ERNs (P4 = N/A); Italian investigator names come from a hospital press release not mirrored on the registry.
A59: Caveat 6 | B59: Chronic disease: Angelman syndrome is a chronic, managed disease — care concentrates at reference centres, so no acute-presentation dispersion caveat applies.
A60: Caveat 7 | B60: Tier 4 not enumerated — not requested.
A61: Caveat 8 | B61: UK post-Brexit: P4 (ERN ITHACA / EpiCARE HCP) = N/A (post-Brexit) for all UK centres; UK tiering uses national leadership, registry and trial signals.
A62: Caveat 9 | B62: P1 gap: no clinician from DE/FR/IT/ES/UK co-authored the 2022 international consensus (Duis et al.). P1 therefore rests on national guidance (FR PNDS 2021; UK 2009 clinical management guidelines; DE diagnostic guideline — EMQN/ACGS 2019 / AWMF S1 — where cited), and Tier 1 in several countries rests on national-equivalent criteria — flagged in Verification_Flags.
A63: Caveat 10 | B63: Evidence limits: live PubMed access was unavailable during this run, so publication scores are conservative (default-low) and KOL Tier 1 = 0 across all countries reflects evidence limits, not influence — re-run PubMed author searches before finalising tiers.
A65: ASSET OVERLAY — obudanersen (ION582, Ionis)
A66: Asset overlay statement | B66: Asset overlay: obudanersen is an intrathecal ASO dosed quarterly (80 mg, no loading regimen) — infrastructure-heavier than oral standard of care but delivered through the same IT-ASO pathway Ionis established with nusinersen (SPINRAZA) and tofersen. Nusinersen-experienced paediatric neurology/SMA centres therefore form a ready-made IT-ASO footprint; the addressable EU4+UK centre base ≈ SMA treatment centres intersected with ERN ITHACA/EpiCARE AS expertise centres, with ex-GTX-102/Aspire and TANGELO sites (ES, DE, UK, FR, IT) as IT-experienced, now-uncommitted trial partners. Key gap: adult LP/sedation capacity and transition services.
A67: Competitor & trial-site tables | B67: See Sources_Caveats → "ASSET & COMPETITOR TRIAL FOOTPRINT" (8 competitor programmes; 33 EU4+UK trial-site rows for REVEAL, HALOS, Aspire, GTX-102 Ph1/2, TANGELO).
A68: Asset fact 1 | B68: Mechanism: obudanersen (ION582) is an investigational 2'-MOE antisense oligonucleotide designed to inhibit expression of the UBE3A antisense transcript (UBE3A-ATS), un-silencing the paternal UBE3A allele and increasing UBE3A protein in neurons. | C68: =HYPERLINK("https://ir.ionis.com/news-releases/news-release-details/ionis-completes-enrollment-pivotal-cohort-phase-3-reveal-study","https://ir.ionis.com/news-releases/news-release-details/ionis-completes-enrollment-pivotal-cohort-phase-3-reveal-study") -> https://ir.ionis.com/news-releases/news-release-details/ionis-completes-enrollment-pivotal-cohort-phase-3-reveal-study
A69: Asset fact 2 | B69: Route: intrathecal (IT) bolus via lumbar puncture; REVEAL/CHAMPION eligibility requires the participant to be able to undergo sedation and/or general anaesthesia without intubation; CHAMPION excludes spinal/brain disease interfering with LP (Chiari, syringomyelia, tethered cord, etc.). | C69: =HYPERLINK("https://clinicaltrials.gov/study/NCT06914609","https://clinicaltrials.gov/study/NCT06914609") -> https://clinicaltrials.gov/study/NCT06914609
A70: Asset fact 3 | B70: REVEAL dosing: originally 3 arms (40 mg, 80 mg, placebo; 2:1 active:placebo, ~200 pts); amended Dec-2025 to 2 arms, 80 mg obudanersen vs control randomised 1:1; 40 mg participants transitioned to 80 mg. Phase 3 design PR (Nov-2024) states quarterly dosing without a loading regimen. | C70: =HYPERLINK("https://clinicaltrials.gov/study/NCT06914609","https://clinicaltrials.gov/study/NCT06914609") -> https://clinicaltrials.gov/study/NCT06914609
A71: Asset fact 4 | B71: Phase 3 design PR (6-Nov-2024): positive End-of-Phase-2 alignment with FDA; primary endpoint = Bayley-4 expressive communication; primary analysis after ~1 year; then open-label LTE. | C71: =HYPERLINK("https://ir.ionis.com/news-releases/news-release-details/ionis-announces-pivotal-phase-3-trial-design-ion582-angelman","https://ir.ionis.com/news-releases/news-release-details/ionis-announces-pivotal-phase-3-trial-design-ion582-angelman") -> https://ir.ionis.com/news-releases/news-release-details/ionis-announces-pivotal-phase-3-trial-design-ion582-angelman
A72: Asset fact 5 | B72: REVEAL (NCT06914609; EU CT 2024-519711-33-00; ION582-CS2): Phase 3 randomised double-blind controlled; ~60-week controlled period, ~25-month LTE, ~8-month follow-up; Cohort 1 = 2–<18 y (population for primary/secondary endpoints), Cohort 2 = 18–≤50 y; UBE3A deletion or mutation only. Study start 2025-06-10; primary completion est. 2027-08; status 'Active, not recruiting', enrolment (actual) 156 (CT.gov last update 2026-09-29). | C72: =HYPERLINK("https://clinicaltrials.gov/study/NCT06914609","https://clinicaltrials.gov/study/NCT06914609") -> https://clinicaltrials.gov/study/NCT06914609
A73: Asset fact 6 | B73: Cohort 1 (pivotal) enrolment completed 6-Jul-2026 with 136 participants aged 2–<18 y; adult Cohort 2 expected to complete enrolment Q3-2026; topline REVEAL data expected 2H-2027. | C73: =HYPERLINK("https://ir.ionis.com/news-releases/news-release-details/ionis-completes-enrollment-pivotal-cohort-phase-3-reveal-study","https://ir.ionis.com/news-releases/news-release-details/ionis-completes-enrollment-pivotal-cohort-phase-3-reveal-study") -> https://ir.ionis.com/news-releases/news-release-details/ionis-completes-enrollment-pivotal-cohort-phase-3-reveal-study
A74: Asset fact 7 | B74: EU control arm: Ionis and EU regulators aligned on a 'skin-prick sham' (needle into skin, no CSF, no injection) in the EU vs placebo elsewhere; FDA and EMA aligned to analyse both control approaches as a single dataset. | C74: =HYPERLINK("https://angelman.org/wp-content/uploads/2026/04/Ionis-REVEAL-sites-EU_community-letter.pdf","https://angelman.org/wp-content/uploads/2026/04/Ionis-REVEAL-sites-EU_community-letter.pdf") -> https://angelman.org/wp-content/uploads/2026/04/Ionis-REVEAL-sites-EU_community-letter.pdf
A75: Asset fact 8 | B75: First EU REVEAL sites activated Apr-2026: Klinikum der LMU München (DE) and Corporació Sanitària Parc Taulí, Hospital de Sabadell (ES); further sites planned in DE, IT, PL, ES; UK already enrolling. | C75: =HYPERLINK("https://angelman.org/wp-content/uploads/2026/04/Ionis-REVEAL-sites-EU_community-letter.pdf","https://angelman.org/wp-content/uploads/2026/04/Ionis-REVEAL-sites-EU_community-letter.pdf") -> https://angelman.org/wp-content/uploads/2026/04/Ionis-REVEAL-sites-EU_community-letter.pdf
A76: Asset fact 9 | B76: Italy: Ionis letter (May-2026) lists actively recruiting Italian REVEAL sites: Fondazione IRCCS Istituto Neurologico Carlo Besta (Milan), AOU Pisana (Pisa), Ospedale Pediatrico Bambino Gesù (Rome). | C76: =HYPERLINK("https://sindromediangelman.org/wp-content/uploads/2026/05/PA-IT-AS-260001-Community-Statement-REVEAL-Opens-in-Italy-052626.pdf","https://sindromediangelman.org/wp-content/uploads/2026/05/PA-IT-AS-260001-Community-Statement-REVEAL-Opens-in-Italy-052626.pdf") -> https://sindromediangelman.org/wp-content/uploads/2026/05/PA-IT-AS-260001-Community-Statement-REVEAL-Opens-in-Italy-052626.pdf
A77: Asset fact 10 | B77: HALOS (NCT05127226) Phase 1/2a open-label MAD + LTE; 51 participants aged 2–50 y; favourable safety at all dose levels; 97% of medium/high-dose participants improved on SAS-CGI-C; Bayley-4 gains in communication, cognition and motor exceeding natural history; improvements on Vineland-3 and ORCA (company-reported, 22-Jul-2024; presented at ASF Family Conference 2024). | C77: =HYPERLINK("https://www.biospace.com/ionis-announces-positive-detailed-results-from-the-halos-study-of-ion582-in-people-with-angelman-syndrome","https://www.biospace.com/ionis-announces-positive-detailed-results-from-the-halos-study-of-ion582-in-people-with-angelman-syndrome") -> https://www.biospace.com/ionis-announces-positive-detailed-results-from-the-halos-study-of-ion582-in-people-with-angelman-syndrome
A78: Asset fact 11 | B78: HALOS topline (16-May-2024): ~65% achieved improvement in Bayley-4 cognition at 6 months; improvements correlated with reduction in EEG slow-wave delta activity; AEs consistent with AS/IT administration; Biogen declined its licence option and Ionis advances ION582 independently. | C78: =HYPERLINK("https://ir.ionis.com/news-releases/news-release-details/ionis-announces-positive-topline-results-phase-12a-trial-ion582","https://ir.ionis.com/news-releases/news-release-details/ionis-announces-positive-topline-results-phase-12a-trial-ion582") -> https://ir.ionis.com/news-releases/news-release-details/ionis-announces-positive-topline-results-phase-12a-trial-ion582
A79: Asset fact 12 | B79: HALOS registry status: Active, not recruiting; 11 locations in 6 countries incl. Necker (Paris), AOU Pisana (Pisa), STRONG Group University of Oxford. | C79: =HYPERLINK("https://eichor.com/study/NCT05127226","https://eichor.com/study/NCT05127226") -> https://eichor.com/study/NCT05127226
A80: Asset fact 13 | B80: No peer-reviewed full HALOS publication identified (Oct-2026); data disseminated via congress/community presentations (Bird L, ASF 2024; Junge C, FAST Global Science Summit Nov-2025) listed on Ionis publications page. | C80: =HYPERLINK("https://ionis.com/taxonomy/term/566","https://ionis.com/taxonomy/term/566") -> https://ionis.com/taxonomy/term/566
A81: Asset fact 14 | B81: CHAMPION (NCT07782827): Phase 3 open-label single-arm study of obudanersen in AS due to paternal UPD or imprinting defect; ~30 participants (2–50 y, two age cohorts); primary = expressive communication; status Recruiting (registry sync 12-Oct-2026), one US site listed (UNC Chapel Hill/Carrboro); no EU sites listed yet. | C81: =HYPERLINK("https://eichor.com/study/NCT07782827","https://eichor.com/study/NCT07782827") -> https://eichor.com/study/NCT07782827
A82: Asset fact 15 | B82: CHAMPION was announced Nov-2025 (FAST Global Science Summit); Ionis July-2026 letter anticipated opening before end-2026. | C82: =HYPERLINK("https://angelman.org/wp-content/uploads/2026/07/Ionis-update-REVEAL-July2026.pdf","https://angelman.org/wp-content/uploads/2026/07/Ionis-update-REVEAL-July2026.pdf") -> https://angelman.org/wp-content/uploads/2026/07/Ionis-update-REVEAL-July2026.pdf
A83: Asset fact 16 | B83: EMA orphan designation EU/3/22/2636 (2'-MOE ASO targeting UBE3A-ATS) granted 21-Jun-2022 to Ionis Development (Ireland) Ltd. | C83: =HYPERLINK("https://www.ema.europa.eu/en/medicines/human/orphan-designations/eu-3-22-2636","https://www.ema.europa.eu/en/medicines/human/orphan-designations/eu-3-22-2636") -> https://www.ema.europa.eu/en/medicines/human/orphan-designations/eu-3-22-2636
A84: Asset fact 17 | B84: FDA Orphan Drug and Rare Pediatric Disease designations (2022) plus FDA Fast Track; EMA orphan designation. No EMA PRIME designation for obudanersen found (PRIME is held by competitor GTX-102). | C84: =HYPERLINK("https://ir.ionis.com/news-releases/news-release-details/ionis-completes-enrollment-pivotal-cohort-phase-3-reveal-study","https://ir.ionis.com/news-releases/news-release-details/ionis-completes-enrollment-pivotal-cohort-phase-3-reveal-study") -> https://ir.ionis.com/news-releases/news-release-details/ionis-completes-enrollment-pivotal-cohort-phase-3-reveal-study
A85: Asset fact 18 | B85: Named investigator quoted by Ionis: Lynne Bird, MD, Professor of Clinical Pediatrics, UC San Diego (HALOS study investigator / PI) — quoted in the 22-Jul-2024 HALOS PR and co-presented HALOS data with an Ionis employee (disclosure slide). No EU4+UK investigator quoted in Ionis press releases identified. | C85: =HYPERLINK("https://ionis.com/sites/default/files/2026-06/Crean%20Bird%20-%20HALOS%20-%20Angelman%20Syndrome%20Program%20Update.pdf","https://ionis.com/sites/default/files/2026-06/Crean%20Bird%20-%20HALOS%20-%20Angelman%20Syndrome%20Program%20Update.pdf") -> https://ionis.com/sites/default/files/2026-06/Crean%20Bird%20-%20HALOS%20-%20Angelman%20Syndrome%20Program%20Update.pdf
A86: Asset fact 19 | B86: Patient-advocacy engagement: Ionis community letters are distributed via the Angelman Syndrome Foundation (angelman.org) and FAST; Ionis presents at ASF Family Conference and FAST Global Science Summit and references community events in Australia, Italy and elsewhere; ORSA (IT) hosted a national family meeting on REVEAL (Pisa, 23-May-2026). A formal contractual 'partnership' is not publicly documented. | C86: =HYPERLINK("https://angelman.org/wp-content/uploads/2025/12/Community-Update-ION582-Ionis_Dec-2025.pdf","https://angelman.org/wp-content/uploads/2025/12/Community-Update-ION582-Ionis_Dec-2025.pdf") -> https://angelman.org/wp-content/uploads/2025/12/Community-Update-ION582-Ionis_Dec-2025.pdf
A87: Asset fact 20 | B87: Ionis neurology IT-ASO heritage: Ionis discovered SPINRAZA (nusinersen, SMA) and QALSODY (tofersen, SOD1-ALS) — both intrathecal ASOs — relevant to the IT-administration footprint argument. | C87: =HYPERLINK("https://ir.ionis.com/news-releases/news-release-details/ionis-completes-enrollment-pivotal-cohort-phase-3-reveal-study","https://ir.ionis.com/news-releases/news-release-details/ionis-completes-enrollment-pivotal-cohort-phase-3-reveal-study") -> https://ir.ionis.com/news-releases/news-release-details/ionis-completes-enrollment-pivotal-cohort-phase-3-reveal-study
A89: KOL GAP-FILL METHODOLOGY (template §5)
A90: Rule | B90: No fabrication. Where P1 guideline authorship or P3 registry coordination does not yield a named KOL for a Tier 2/3 centre, gap-fill in this order:
A91: (a) P2 publication signal | B91: Senior/corresponding author on the centre's AS papers or asset/competitor-trial papers; trial site PI where public.
A92: (b) Reference-network coordinator | B92: ERN ITHACA / EpiCARE HCP coordinator or Orphanet expert-centre lead.
A93: (c) National network coordinator | B93: National rare-disease / specialty-network coordinator (e.g. FR CRMR/CCMR, DE ZSE, ES CSUR, IT regional networks).
A94: (d) Registry / database authorship | B94: Authorship on a relevant national/consortium database or registry paper.
A95: Fallback | B95: Hospital directories / local sources; if still untraceable the cell reads "Not publicly identified — verify locally".
A97: HOW TO USE
A98: Field deployment | B98: Country_Centres → sort by Tier (ascending) then Country; Tier 1 = first-wave advisory/evidence-partner engagement, Tier 2 = second wave, Tier 3 = launch-phase education.
A99: Trial-site shortlist | B99: Country_Centres → filter P3 contains "Site" AND P2 begins "Yes" (then review P2 for "ION582" vs competitor-trial signal and Infrastructure for IT-LP/sedation capacity).
A100: Verification reminder | B100: Re-verify affiliation and current trial activity before any outreach; resolve every red-highlighted cell via Verification_Flags (flags are not auto-corrected).
A101: Compliance | B101: Check industry-payment / transfer-of-value disclosures (FSA/EFPIA, Transparence Santé, Farmaindustria, Disclosure UK) for KOLs flagged as competitor-trial PIs before contracting.
A102: Counts | B102: Tier_Counts recalculates automatically from the data tabs — edit the data, not the counts.

Sheet Country_Centres
A1: Country_Centres — EU4+UK Angelman syndrome treatment centres (Tiers 1–3), obudanersen (ION582) mapping
A2: Country | B2: Tier | C2: City | D2: Centre / Hospital | E2: Unit / Department | F2: KOL / Lead clinician(s) | G2: Role / Affiliation signal | H2: P1 — Consensus 2022 / national guideline author | I2: P2 — AS publications / ION582 or competitor trial (5y) | J2: P3 — AS registry / trial-network coord/site | K2: P4 — ERN ITHACA / EpiCARE HCP | L2: P5 — Angelman clinic / programme | M2: Notes
A3: France | B3: 1 | C3: Paris | D3: AP-HP Sorbonne Université — Groupe Hospitalier Pitié-Salpêtrière | E3: Département de Génétique (UF Génétique clinique) — CRMR coordonnateur Déficiences Intellectuelles de causes rares (Filière DéfiScience); Neurologie (adult AS); Pédopsychiatrie | F3: Dr Delphine Héron; Dr Perrine Charles; Pr Angèle Consoli | G3: PNDS Angelman coordinator (Dr Héron) and national CRMR DI coordinator; ERN ITHACA Paris consortium (DéfiScience axis); 3 AFSA Conseil Médical et Scientifique members on site | H3: Yes — national guideline (PNDS Syndrome d'Angelman, Nov 2021, CRMR DI de causes rares) — coordinating centre/author (Héron) | I3: Yes — disease (qualified): PNDS + argumentaire 2021 (systematic review of 249 studies) authored by this CRMR; individual AS peer-reviewed papers 2021–26 not verified in this pass | J3: No — no French site on REVEAL (NCT06914609; 41 sites, none in FR) or Aspire (NCT06617429; EU sites DE/PL/ES); national registry (BNDMR) participation not verified | K3: Yes — ITHACA (AP-HP Paris consortium) + national CRMR coordinator (DéfiScience) | L3: Yes — national AS expertise hub (PNDS-issuing CRMR; adult AS follow-up via neurology; AFSA CMS) | M3: Natural FR advisory-board anchor and ION582 evidence-partner candidate. Tier 1 is provisional: P2 rests on the PNDS/argumentaire, not verified peer-reviewed AS papers. PNDS contact: UF de Génétique clinique, 47-83 bd de l'Hôpital, Paris 13. CRMR DI also spans Hôpital Armand-Trousseau. Sources: https://www.has-sante.fr/upload/docs/application/pdf/2021-11/pnds_angelman_vf_.doc.pdf; https://www.has-sante.fr/upload/docs/application/pdf/2021-11/argumentaire_pnds_angelman_vf.pdf; https://www.has-sante.fr/jcms/p_3300847/fr/syndrome-d-angelman; https://ern-ithaca.eu/about-us/expert-centers/ern-ithaca-paris-center-robert-debre-university-hospital/; https://www.angelman-afsa.org/afsa/son-equipe/conseil-medical-et-scientifique/afsa/son-equipe/conseil-medical-et-scientifique/le-conseil-medical-et-scientifique
A4: France | B4: 1 | C4: Paris | D4: AP-HP Hôpital Necker-Enfants Malades | E4: Neuropédiatrie — CRMR DI de causes rares et polyhandicap; CRéER (Centre de référence épilepsies rares) site constitutif; Génétique clinique | F4: Dr Nadia Bahi-Buisson; Dr Marie Hully; Pr Rima Nabbout; Dr Marlène Rio | G4: French coordinating centre for obudanersen Phase 1/2 HALOS (ION582-CS1). Dr Bahi-Buisson is the coordinating investigator and also coordinates the GTX-102 Phase 2 basket study (GTX-102-CL210). The centre also has EpiCARE (HCP coordinator Nabbout), ITHACA Paris and former AFSA CMS president (Hully) signals. | H4: No (individual PNDS authorship not verified; AFSA CMS, chaired by Hully, finalised the PNDS 2021) | I4: Yes — ION582 trial (HALOS NCT05127226) + Yes — competitor trial (GTX-102 Ph1/2 NCT04259281 site; GTX-102 Ph2 basket CL210 national coordinator; GTX-102 LTE CL302 recruiting site) | J4: Site — ION582 HALOS (French national coordinating centre per AP-HP trial registry; opened Jun-2023). Also Site — competitor (GTX-102 Ph1/2, Ph2 basket, LTE). Not a REVEAL site. | K4: Yes — ITHACA+EpiCARE | L4: Yes — AS explicitly in CRéER rare-epilepsy scope; CRMR DI/polyhandicap neuropaediatrics | M4: Re-tiered 2→1. The ITHACA+EpiCARE (P4) and HALOS plus GTX-102 trial authorship/PI roles (P2) criteria are met. The P1/P3-coordinator arm is met only by reading 'national coordinating centre of the asset's Ph1/2 trial' as a P3 coordinator role; no registry coordinator or PNDS author is verified here (see flag). This is the only French centre with intrathecal UBE3A-ASO dosing experience (ION582 and GTX-102), making it the primary ION582 evidence partner, REVEAL/CHAMPION site candidate and HALOS-LTE continuity site. HALOS is active, not recruiting; the AP-HP entry is closed to inclusion. Sources: https://www.aphp.fr/registre-des-essais-cliniques/etude-visant-evaluer-la-securite-la-tolerance-la-pharmacocinetique-et; https://eichor.com/study/NCT05127226; https://www.fastfrance.org/dossier-angelman/ionis-syndrome-dangelman/; https://www.aphp.fr/registre-des-essais-cliniques/etude-en-ouvert-de-phase-2-de-type-panier-visant-evaluer-linnocuite; https://hopital-broca.aphp.fr/registre-des-essais-cliniques/etude-dextension-long-terme-portant-sur-la-securite-demploi-et-65; https://clinicaltrials.gov/study/NCT04259281; https://epi-care.eu/hospitals/necker-enfants-malades-aphp/; https://maladiesrares-necker.aphp.fr/rare-epilepsies/; https://ern-ithaca.eu/about-us/expert-centers/ern-ithaca-paris-center-robert-debre-university-hospital/
A5: France | B5: 1 | C5: Marseille | D5: AP-HM Hôpital de la Timone Enfants | E5: Neurologie pédiatrique — CRéER coordinating centre (épilepsies rares) + CRMR DI/polyhandicap site | F5: Dr Béatrice Desnous; Pr Mathieu Milh | G5: Pr Milh is the national coordinating investigator of the GTX-102 long-term extension (GTX-102-CL302). The centre was a GTX-102 Ph1/2 site and is the CRéER coordinating centre; Dr Desnous is current AFSA CMS president. | H5: No (PNDS authorship not verified) | I5: Yes — competitor trial (GTX-102 Ph1/2 NCT04259281 site; GTX-102 LTE CL302 national coordinator) | J5: Coordinator (national) — competitor GTX-102 LTE CL302. Also Site — competitor (GTX-102 Ph1/2). No ION582 site. | K5: National CRMR (CRéER coordinating centre; CRMR DI site). ERN EpiCARE/ITHACA membership not verified. | L5: Yes — AS-engaged neuropaediatrics (AFSA CMS presidency) within rare-epilepsy/DI reference programme | M5: Re-tiered 2→1 on the competitor-trial national coordinator role, the national CRMR coordinator role (P4 national analogue per brief) and competitor-trial P2. Displaceable, intrathecal-ASO-experienced site: high value for REVEAL/CHAMPION expansion now that Aspire has failed (2-Sep-2026). The LTE status after Aspire is uncertain, so verify. Confirm ERN membership. Sources: https://www.angelman-afsa.org/afsa/son-equipe/conseil-medical-et-scientifique/afsa/son-equipe/conseil-medical-et-scientifique/le-conseil-medical-et-scientifique; https://stxbp1eu.org/france/; https://kcnq2francedeveloppement.fr/pole-recherche/; https://maladiesrares-necker.aphp.fr/rare-epilepsies/; https://hopital-broca.aphp.fr/registre-des-essais-cliniques/etude-dextension-long-terme-portant-sur-la-securite-demploi-et-65; https://clinicaltrials.gov/study/NCT04259281
A6: France | B6: 2 | C6: Paris | D6: AP-HP Hôpital Robert-Debré | E6: Département de Génétique — CRMR coordonnateur CLAD Île-de-France (AnDDI-Rares); ERN ITHACA EU coordinating centre | F6: Pr Alain Verloes; Dr David Germanaud | G6: ERN ITHACA EU coordinator (Verloes, since 2018); CLAD-IDF coordinator; ITHACA Paris consortium (Germanaud, DéfiScience axis) | H6: No (not verified as PNDS contributor) | I6: No AS-specific 2021–26 publication verified | J6: No — no French site on REVEAL (NCT06914609; 41 sites, none in FR) or Aspire (NCT06617429; EU sites DE/PL/ES) | K6: Yes — ITHACA (EU coordinating centre) | L6: Partial — developmental anomalies / neurodevelopmental genetics programme | M6: European-network gateway (ITHACA guidance/endorsement, CPMS). Not AS-research-active on current evidence; engage for network-level RWE and ERN guidance. Sources: https://ern-ithaca.eu/about-us/expert-centers/ern-ithaca-paris-center-robert-debre-university-hospital/; https://ern-ithaca.eu/about-us/who-we-are/; https://robertdebre.aphp.fr/centre-de-reference-des-anomalies-du-developpement-syndromes-malformatif-dile-de-france
A7: France | B7: 2 | C7: Paris | D7: AP-HP Sorbonne Université — Hôpital Armand-Trousseau | E7: Neuropédiatrie & Génétique — CRMR DI de causes rares (site), ITHACA Paris consortium | F7: Dr Stéphanie Valence; Dr Nathalie Dorison | G7: ITHACA Paris consortium (Valence, child neurology); historic AFSA CMS member (Dorison); AFSA CMS psychologist on site | H7: No (not verified) | I7: No AS-specific 2021–26 paper verified | J7: No — no French site on REVEAL (NCT06914609; 41 sites, none in FR) or Aspire (NCT06617429; EU sites DE/PL/ES) | K7: Yes — ITHACA (AP-HP Paris consortium) + CRMR DI site | L7: Partial — DI/neurodevelopmental programme; AS experience via AFSA CMS | M7: Part of the Pitié–Trousseau CRMR DI pairing named in the PNDS contact block. Sources: https://ern-ithaca.eu/about-us/expert-centers/ern-ithaca-paris-center-robert-debre-university-hospital/; https://www.has-sante.fr/upload/docs/application/pdf/2021-11/pnds_angelman_vf_.doc.pdf; https://www.livret-angelman-afsa.org/les-contributeurs; https://www.angelman-afsa.org/afsa/son-equipe/conseil-medical-et-scientifique/afsa/son-equipe/conseil-medical-et-scientifique/le-conseil-medical-et-scientifique
A8: France | B8: 2 | C8: Lyon (Bron) | D8: Hospices Civils de Lyon — Hôpital Femme-Mère-Enfant | E8: Service de génétique — CLAD Sud-Est coordinator; CRDI (DéfiScience); Child Neurology | F8: Dr Massimiliano Rossi | G8: ERN ITHACA Lyon centre lead; CRDI coordinates DéfiScience per ITHACA page; AURAGEN genome platform | H8: No | I8: No AS-specific 2021–26 paper verified | J8: No — no French site on REVEAL (NCT06914609; 41 sites, none in FR) or Aspire (NCT06617429; EU sites DE/PL/ES) | K8: Yes — ITHACA | L8: Partial — ID/neurodevelopment genetics programme | M8: Regional hub for Grenoble, Saint-Étienne, Clermont-Ferrand, Marseille, Nice and Toulon genetics. Sources: https://ern-ithaca.eu/about-us/expert-centers/ern-ithaca-lyon-center/
A9: France | B9: 2 | C9: Dijon | D9: CHU Dijon Bourgogne — Hôpital d'Enfants | E9: Centre de Génétique — CRMR Anomalies du développement; FHU TRANSLAD | F9: Pr Laurence Faivre | G9: ERN ITHACA Dijon centre lead; FHU-TRANSLAD coordination (genomic medicine in developmental disorders) | H9: No | I9: No AS-specific 2021–26 paper verified (NDD episignature co-authorship 2024, PMID 37872275) | J9: No — no French site on REVEAL (NCT06914609; 41 sites, none in FR) or Aspire (NCT06617429; EU sites DE/PL/ES) | K9: Yes — ITHACA | L9: Partial — developmental disorders/ID genetics programme | M9: Strong translational/genomic-medicine infrastructure; potential RWE partner. Sources: https://ern-ithaca.eu/about-us/expert-centers/ern-ithaca-dijon-center/; https://pubmed.ncbi.nlm.nih.gov/37872275/
A10: France | B10: 3 | C10: Brest | D10: CHU de Brest | E10: Neuropédiatrie | F10: Dr Sylviane Peudenier | G10: AFSA CMS president for 7 years (predecessor of Hully); SFNP DI commission | H10: No (not verified) | I10: No | J10: No | K10: Not verified | L10: Partial — AS-experienced neuropaediatrics | M10: Affiliation/activity currency to verify. Sources: https://www.livret-angelman-afsa.org/les-contributeurs; https://www.angelman-afsa.org/afsa/son-equipe/conseil-medical-et-scientifique/nouvelle-presidence-du-cms
A11: France | B11: 3 | C11: Toulon | D11: Centre Hospitalier Intercommunal Toulon–La Seyne | E11: Génétique médicale (CLAD Sud-Est network site) | F11: Dr Florence Riccardi | G11: Current AFSA CMS member (geneticist) | H11: No | I11: No | J11: No | K11: No (CLAD Sud-Est network site via Lyon) | L11: Partial | M11: Non-university hospital; included because of named AS-engaged geneticist. Sources: https://www.angelman-afsa.org/afsa/son-equipe/conseil-medical-et-scientifique/afsa/son-equipe/conseil-medical-et-scientifique/le-conseil-medical-et-scientifique; https://ern-ithaca.eu/about-us/expert-centers/ern-ithaca-lyon-center/
A12: France | B12: 3 | C12: Paris | D12: GHU Paris Psychiatrie & Neurosciences (Sainte-Anne) | E12: Psychiatrie | F12: Dr Boris Chaumette | G12: Current AFSA CMS member (psychiatrist — behavioural/psychiatric AS phenotype) | H12: No | I12: No | J12: No | K12: No | L12: Partial — psychiatry of genetic NDD | M12: Behaviour/psychiatry voice for advisory boards. Sources: https://www.angelman-afsa.org/afsa/son-equipe/conseil-medical-et-scientifique/afsa/son-equipe/conseil-medical-et-scientifique/le-conseil-medical-et-scientifique
A13: France | B13: 3 | C13: Aix-en-Provence | D13: Centre Hospitalier du Pays d'Aix | E13: Neuropédiatrie | F13: Dr Marie-Odile Livet | G13: Historic AFSA CMS member; co-author of foundational French AS genotype-phenotype series (Moncla et al. 1999) | H13: No | I13: No (historic only) | J13: No | K13: No | L13: Partial | M13: Likely retired/inactive — verify before outreach. Sources: https://www.livret-angelman-afsa.org/les-contributeurs; https://www.has-sante.fr/upload/docs/application/pdf/2021-11/argumentaire_pnds_angelman_vf.pdf
A14: France | B14: 3 | C14: Lille | D14: CHU de Lille | E14: Clinique de génétique Guy Fontaine | F14: Not publicly identified — verify locally | G14: University genetics service active in national NDD genomics (episignature consortium) | H14: No | I14: No AS-specific | J14: No | K14: Not verified | L14: Partial | M14: Sources: https://pubmed.ncbi.nlm.nih.gov/37872275/
... A97: United Kingdom | B97: 3 | C97: Southampton | D97: University Hospital Southampton NHS FT — Princess Anne Hospital | E97: Wessex Clinical Genetics Service (and Wessex congenital anomaly registry linkage via EUROCAT/EUROlinkCAT) | F97: Dr Diana Gay Wellesley (Consultant Clinical Geneticist); Prof Joan K Morris (City St George's, University of London — epidemiology collaborator, last author) | G97: UK co-author of 2025 European population-based AS/PWS health-outcomes study (EUROlinkCAT) | H97: No | I97: Yes — disease (Abate MV…Wellesley DG, Morris JK. Arch Dis Child 2025;110(11):899-904; doi:10.1136/archdischild-2025-328786; PMID 40484454) — epidemiology, single paper | J97: No (congenital-anomaly registry linkage, not an AS registry/trial site) | K97: N/A (post-Brexit) — national analogue: Wessex regional clinical genetics service | L97: Partial (regional clinical genetics) | M97: Tier 3: tertiary capable; RWE/epidemiology value (registry-linked healthcare-utilisation data for AS) rather than trial readiness. Sources: https://adc.bmj.com/content/110/11/899; https://pure.ulster.ac.uk/ws/portalfiles/portal/221906804/Prader-Willi_Angelman_syndrome_-_accepted_version.pdf

Sheet KOL_Roster
A1: KOL_Roster — named Angelman syndrome KOLs, EU4+UK (scored per template §3; Tier 1 = 24–30, Tier 2 = 12–23, Tier 3 = 0–11)
A2: Country | B2: KOL | C2: Primary affiliation | D2: Role/Signal | E2: P1 guideline author | F2: P3 registry role | G2: Key publications/datasets (P2) | H2: Presentation at international conferences | I2: Engagement priority | J2: KOL Tier for TOV | K2: Score — Guideline authorship | L2: Score — Publications | M2: Score — Clinical trials | N2: Score — Academic appointment | O2: Score — Society roles | P2: Score — Speaker engagement | Q2: Score — Awards | R2: Total score | S2: Sources
A3: France | B3: Dr Delphine Héron | C3: AP-HP Pitié-Salpêtrière (Sorbonne Université), Génétique clinique; coordinator CRMR DI de causes rares (DéfiScience) | D3: PNDS Syndrome d'Angelman coordinator (2021); national CRMR DI coordinator; ITHACA Paris consortium; AFSA CMS member | E3: Yes — PNDS Angelman 2021 (coordinator) | F3: No (no FR REVEAL/Aspire site) | G3: PNDS + argumentaire Syndrome d'Angelman (HAS, Nov 2021). Peer-reviewed AS papers 2021–26 not verified in this pass. | H3: Not identified in this pass — verify (ASA/ASF/FAST congress programmes) | I3: TIER 2 — engage (national anchor; first-wave advisory-board lead despite score) | J3: =IF(R3>=24,1,IF(R3>=12,2,3)) -> 2 | K3: 3 | L3: 1 | M3: 1 | N3: 3 | O3: 3 | P3: 1 | Q3: 0 | R3: =SUM(K3:Q3) -> 12 | S3: https://www.has-sante.fr/upload/docs/application/pdf/2021-11/pnds_angelman_vf_.doc.pdf; https://www.has-sante.fr/upload/docs/application/pdf/2021-11/argumentaire_pnds_angelman_vf.pdf; https://ern-ithaca.eu/about-us/expert-centers/ern-ithaca-paris-center-robert-debre-university-hospital/; https://www.angelman-afsa.org/afsa/son-equipe/conseil-medical-et-scientifique/afsa/son-equipe/conseil-medical-et-scientifique/le-conseil-medical-et-scientifique
A4: France | B4: Pr Rima Nabbout | C4: AP-HP Necker-Enfants Malades / Institut Imagine — CRéER (rare epilepsies) | D4: EpiCARE HCP coordinator & founding steering member; chairs BNDMR scientific committee; PI of international/industry rare-epilepsy trials | E4: No (AS) | F4: BNDMR scientific-committee chair (national rare-disease database, not AS-specific); No (no FR REVEAL/Aspire site) | G4: Rare/developmental-epilepsy output (e.g., KCNT1, fenfluramine DEE reviews listed on Imagine profile); AS-specific papers not verified | H4: ILAE working groups — specific oral presentations to verify | I4: TIER 2 — high value — epilepsy/trial-readiness anchor (not AS-specific) | J4: =IF(R4>=24,1,IF(R4>=12,2,3)) -> 2 | K4: 1 | L4: 5 | M4: 5 | N4: 5 | O4: 5 | P4: 1 | Q4: 0 | R4: =SUM(K4:Q4) -> 22 | S4: https://www.institutimagine.org/en/users/rimanabboutaphpfr; https://epi-care.eu/hospitals/necker-enfants-malades-aphp/; https://maladiesrares-necker.aphp.fr/rare-epilepsies/
A5: France | B5: Dr Nadia Bahi-Buisson | C5: AP-HP Necker-Enfants Malades — Neurologie pédiatrique | D5: Coordinating investigator in France for obudanersen HALOS (ION582-CS1, Necker); coordinating investigator for GTX-102 Ph2 basket (GTX-102-CL210); ERN ITHACA Paris consortium (DéfiScience axis) | E5: No | F5: Site — ION582 HALOS (FR coordinating investigator); Site — competitor (GTX-102 CL210 coordinator; CL302 LTE recruiting at Necker) | G5: Investigator/PI roles: HALOS NCT05127226 (ION582-CS1, FR coordinating investigator); GTX-102-CL210 Ph2 basket (FR coordinating investigator). AS peer-reviewed papers not verified (PubMed check pending). | H5: Not identified in this pass — verify (ASA/ASF/FAST congress programmes) | I5: TIER 2 — must-engage (ION582-specific) — HALOS investigator; also competitor-trial PI | J5: =IF(R5>=24,1,IF(R5>=12,2,3)) -> 2 | K5: 1 | L5: 1 | M5: 5 | N5: 3 | O5: 1 | P5: 1 | Q5: 0 | R5: =SUM(K5:Q5) -> 12 | S5: https://www.aphp.fr/registre-des-essais-cliniques/etude-visant-evaluer-la-securite-la-tolerance-la-pharmacocinetique-et; https://www.aphp.fr/registre-des-essais-cliniques/etude-en-ouvert-de-phase-2-de-type-panier-visant-evaluer-linnocuite; https://ern-ithaca.eu/about-us/expert-centers/ern-ithaca-paris-center-robert-debre-university-hospital/
A6: France | B6: Pr Alain Verloes | C6: AP-HP Robert-Debré — Head, Clinical Genetics Department; CLAD-IDF coordinator | D6: ERN ITHACA EU coordinator (since 2018) | E6: No (AS) | F6: No (no FR REVEAL/Aspire site) | G6: AS-specific output not verified (verify PubMed) | H6: ERN ITHACA/ESHG meetings — verify specific talks | I6: TIER 2 — engage (ERN network gateway) | J6: =IF(R6>=24,1,IF(R6>=12,2,3)) -> 2 | K6: 1 | L6: 1 | M6: 1 | N6: 5 | O6: 5 | P6: 1 | Q6: 0 | R6: =SUM(K6:Q6) -> 14 | S6: https://ern-ithaca.eu/about-us/who-we-are/; https://ern-ithaca.eu/about-us/expert-centers/ern-ithaca-paris-center-robert-debre-university-hospital/; https://robertdebre.aphp.fr/centre-de-reference-des-anomalies-du-developpement-syndromes-malformatif-dile-de-france
A7: France | B7: Pr Mathieu Milh | C7: AP-HM La Timone Enfants — Neurologie pédiatrique | D7: Heads national reference centres for rare epilepsies (CRéER coordinator) and rare severe developmental disorders; national coordinating investigator, GTX-102 LTE (GTX-102-CL302) | E7: No | F7: Coordinator (national) — competitor GTX-102 LTE CL302; Timone GTX-102 Ph1/2 site | G7: STXBP1 French cohort phenotyping (per ESCO profile); AS-specific output not verified; GTX-102-CL302 LTE national coordinating investigator | H7: Not identified in this pass — verify (ASA/ASF/FAST congress programmes) | I7: TIER 2 — high value — competitor-trial PI (displaceable after Aspire failure) | J7: =IF(R7>=24,1,IF(R7>=12,2,3)) -> 2 | K7: 1 | L7: 1 | M7: 3 | N7: 5 | O7: 3 | P7: 1 | Q7: 0 | R7: =SUM(K7:Q7) -> 14 | S7: https://stxbp1eu.org/france/; https://kcnq2francedeveloppement.fr/pole-recherche/; https://maladiesrares-necker.aphp.fr/rare-epilepsies/; https://hopital-broca.aphp.fr/registre-des-essais-cliniques/etude-dextension-long-terme-portant-sur-la-securite-demploi-et-65; https://clinicaltrials.gov/study/NCT04259281
A8: France | B8: Pr Laurence Faivre | C8: CHU Dijon Bourgogne — Centre de Génétique; FHU TRANSLAD | D8: ERN ITHACA Dijon lead | E8: No | F8: No (no FR REVEAL/Aspire site) | G8: NDD episignature co-author EJHG 2024 (PMID 37872275); AS-specific not verified | H8: Not identified in this pass — verify (ASA/ASF/FAST congress programmes) | I8: TIER 2 — engage (genomic-medicine/RWE partner) | J8: =IF(R8>=24,1,IF(R8>=12,2,3)) -> 2 | K8: 1 | L8: 1 | M8: 1 | N8: 5 | O8: 3 | P8: 1 | Q8: 0 | R8: =SUM(K8:Q8) -> 12 | S8: https://ern-ithaca.eu/about-us/expert-centers/ern-ithaca-dijon-center/; https://pubmed.ncbi.nlm.nih.gov/37872275/
A9: France | B9: Dr Perrine Charles | C9: AP-HP Pitié-Salpêtrière — Neurologie / CRMR DI de causes rares | D9: AFSA CMS neurologist; adult AS follow-up (AFSA adult-transition training 2021) | E9: No (individual PNDS role not verified) | F9: No (no FR REVEAL/Aspire site) | G9: Co-author, NDD episignature evaluation, Eur J Hum Genet 2024;32:190-199 (PMID 37872275; not AS-specific) | H9: Not identified in this pass — verify (ASA/ASF/FAST congress programmes) | I9: TIER 3 — monitor (adult-AS voice; REVEAL adult-cohort relevance) | J9: =IF(R9>=24,1,IF(R9>=12,2,3)) -> 3 | K9: 1 | L9: 1 | M9: 1 | N9: 1 | O9: 3 | P9: 1 | Q9: 0 | R9: =SUM(K9:Q9) -> 8 | S9: https://www.angelman-afsa.org/afsa/son-equipe/conseil-medical-et-scientifique/afsa/son-equipe/conseil-medical-et-scientifique/le-conseil-medical-et-scientifique; https://www.angelman-afsa.org/fichiers/Rapport%20d'Activites%202021-1654173306.pdf; https://pubmed.ncbi.nlm.nih.gov/37872275/
A10: France | B10: Pr Angèle Consoli | C10: AP-HP Pitié-Salpêtrière — Pédopsychiatrie | D10: AFSA CMS child psychiatrist; AFSA family-handbook author | E10: No (not verified) | F10: No (no FR REVEAL/Aspire site) | G10: AFSA livret contributor (behaviour); AS peer-reviewed output not verified | H10: Not identified in this pass — verify (ASA/ASF/FAST congress programmes) | I10: TIER 3 — monitor (behaviour endpoints voice) | J10: =IF(R10>=24,1,IF(R10>=12,2,3)) -> 3 | K10: 1 | L10: 1 | M10: 1 | N10: 3 | O10: 3 | P10: 1 | Q10: 0 | R10: =SUM(K10:Q10) -> 10 | S10: https://www.angelman-afsa.org/afsa/son-equipe/conseil-medical-et-scientifique/afsa/son-equipe/conseil-medical-et-scientifique/le-conseil-medical-et-scientifique; https://www.livret-angelman-afsa.org/les-contributeurs
A11: France | B11: Dr Marie Hully | C11: AP-HP Necker-Enfants Malades — Neuropédiatrie (CRMR DI & polyhandicap) and Rééducation pédiatrique | D11: Former AFSA CMS president (succeeded Peudenier); head SFNP Commission Handicaps et Déficiences Intellectuelles | E11: Contributor via AFSA CMS (CMS finalised PNDS 2021) — individual authorship unverified | F11: No (no FR REVEAL/Aspire site) | G11: AS peer-reviewed output not verified | H11: Not identified in this pass — verify (ASA/ASF/FAST congress programmes) | I11: TIER 3 — monitor; upgrade candidate (AS clinic lead at Necker — verify) | J11: =IF(R11>=24,1,IF(R11>=12,2,3)) -> 3 | K11: 1 | L11: 1 | M11: 1 | N11: 3 | O11: 3 | P11: 1 | Q11: 0 | R11: =SUM(K11:Q11) -> 10 | S11: https://www.angelman-afsa.org/afsa/son-equipe/conseil-medical-et-scientifique/nouvelle-presidence-du-cms; https://www.angelman-afsa.org/afsa/son-equipe/conseil-medical-et-scientifique/afsa/son-equipe/conseil-medical-et-scientifique/le-conseil-medical-et-scientifique; https://www.angelman-afsa.org/fichiers/Rapport%20d'Activites%202021-1654173306.pdf
A12: France | B12: Dr Marlène Rio | C12: AP-HP Necker-Enfants Malades — Génétique | D12: ERN ITHACA Paris consortium member (DéfiScience axis) | E12: No | F12: No (no FR REVEAL/Aspire site) | G12: AS-specific output not verified | H12: Not identified in this pass — verify (ASA/ASF/FAST congress programmes) | I12: TIER 3 — monitor | J12: =IF(R12>=24,1,IF(R12>=12,2,3)) -> 3 | K12: 1 | L12: 1 | M12: 1 | N12: 1 | O12: 1 | P12: 1 | Q12: 0 | R12: =SUM(K12:Q12) -> 6 | S12: https://ern-ithaca.eu/about-us/expert-centers/ern-ithaca-paris-center-robert-debre-university-hospital/
A13: France | B13: Dr David Germanaud | C13: AP-HP Robert-Debré — Génétique | D13: ERN ITHACA Paris consortium member (DéfiScience axis) | E13: No | F13: No (no FR REVEAL/Aspire site) | G13: AS-specific output not verified | H13: Not identified in this pass — verify (ASA/ASF/FAST congress programmes) | I13: TIER 3 — monitor | J13: =IF(R13>=24,1,IF(R13>=12,2,3)) -> 3 | K13: 1 | L13: 1 | M13: 1 | N13: 1 | O13: 1 | P13: 1 | Q13: 0 | R13: =SUM(K13:Q13) -> 6 | S13: https://ern-ithaca.eu/about-us/expert-centers/ern-ithaca-paris-center-robert-debre-university-hospital/
A14: France | B14: Dr Béatrice Desnous | C14: AP-HM La Timone Enfants — Neurologie pédiatrique (CRéER / CRMR DI) | D14: Current AFSA CMS president; MD-PhD child neurologist/neurophysiologist | E14: No (not verified) | F14: No (no FR REVEAL/Aspire site) | G14: Genetic NDD/STXBP1 clinical studies; AS-specific output not verified | H14: Not identified in this pass — verify (ASA/ASF/FAST congress programmes) | I14: TIER 3 — monitor; high community value (AFSA CMS president) | J14: =IF(R14>=24,1,IF(R14>=12,2,3)) -> 3 | K14: 1 | L14: 1 | M14: 1 | N14: 3 | O14: 3 | P14: 1 | Q14: 0 | R14: =SUM(K14:Q14) -> 10 | S14: https://www.angelman-afsa.org/afsa/son-equipe/conseil-medical-et-scientifique/afsa/son-equipe/conseil-medical-et-scientifique/le-conseil-medical-et-scientifique; https://stxbp1eu.org/france/; https://kcnq2francedeveloppement.fr/pole-recherche/
... A99: United Kingdom | B99: Hayley Denyer | C99: UCL Great Ormond Street Institute of Child Health (per 2019 affiliation — verify) | D99: [Non-physician — psychologist/researcher] Researcher; AS sleep co-author | E99: No | F99: No | G99: Co-author Front Psychiatry 2019;10:874 | H99: Not verified | I99: TIER 3 — monitor — verify current affiliation (GOSH link) | J99: =IF(R99>=24,1,IF(R99>=12,2,3)) -> 3 | K99: 1 | L99: 1 | M99: 1 | N99: 1 | O99: 1 | P99: 1 | Q99: 0 | R99: =SUM(K99:Q99) -> 6 | S99: https://doaj.org/article/6fdb3ab1e55c4c2f9932c00ad98c1c89

Sheet Tier_Counts
A1: Tier_Counts — centres and KOLs by country × tier (all counts are live COUNTIFS on Country_Centres / KOL_Roster)
A3: A. CENTRES × COUNTRY × TIER
A4: Country | B4: Tier 1 | C4: Tier 2 | D4: Tier 3 | E4: Tier 4 | F4: Total enumerated | G4: Notes
A5: France | B5: =COUNTIFS(Country_Centres!$A$3:$A$97,$A5,Country_Centres!$B$3:$B$97,1) -> 3 | C5: =COUNTIFS(Country_Centres!$A$3:$A$97,$A5,Country_Centres!$B$3:$B$97,2) -> 4 | D5: =COUNTIFS(Country_Centres!$A$3:$A$97,$A5,Country_Centres!$B$3:$B$97,3) -> 10 | E5: =COUNTIFS(Country_Centres!$A$3:$A$97,$A5,Country_Centres!$B$3:$B$97,4) -> 0 | F5: =COUNTIF(Country_Centres!$A$3:$A$97,$A5) -> 17 | G5: Tier 4: not enumerated — not requested. France's national P1 anchor is Pitié-Salpêtrière (PNDS 2021). Its trial anchors are Necker (ION582 HALOS coordinating centre, plus GTX-102) and Timone (GTX-102 Ph1/2 and LTE coordination). Neither hosts REVEAL. KOL scores stay low pending a verified PubMed sweep.
A6: Germany | B6: =COUNTIFS(Country_Centres!$A$3:$A$97,$A6,Country_Centres!$B$3:$B$97,1) -> 3 | C6: =COUNTIFS(Country_Centres!$A$3:$A$97,$A6,Country_Centres!$B$3:$B$97,2) -> 4 | D6: =COUNTIFS(Country_Centres!$A$3:$A$97,$A6,Country_Centres!$B$3:$B$97,3) -> 10 | E6: =COUNTIFS(Country_Centres!$A$3:$A$97,$A6,Country_Centres!$B$3:$B$97,4) -> 0 | F6: =COUNTIF(Country_Centres!$A$3:$A$97,$A6) -> 17 | G6: Tier 4: not enumerated — not requested. Germany's AS care is concentrated in three Angelman e.V./ASF-recognised centres: Munich (paediatric; first EU REVEAL site), Leipzig (paediatric + national AS registry) and Aachen (adults). Diagnostic leadership sits in Essen (EMQN/ACGS and AWMF guideline authors). Tier 1 rests partly on national-analogue pillars because no German clinician authored the 2022 international consensus and none of the three AS centres is an ERN ITHACA HCP. ERN ITHACA/EpiCARE HCPs without AS activity are placed in Tiers 2–3.
A7: Italy | B7: =COUNTIFS(Country_Centres!$A$3:$A$97,$A7,Country_Centres!$B$3:$B$97,1) -> 1 | C7: =COUNTIFS(Country_Centres!$A$3:$A$97,$A7,Country_Centres!$B$3:$B$97,2) -> 11 | D7: =COUNTIFS(Country_Centres!$A$3:$A$97,$A7,Country_Centres!$B$3:$B$97,3) -> 16 | E7: =COUNTIFS(Country_Centres!$A$3:$A$97,$A7,Country_Centres!$B$3:$B$97,4) -> 0 | F7: =COUNTIF(Country_Centres!$A$3:$A$97,$A7) -> 28 | G7: Tier 4: not enumerated — not requested. Italy has no national AS guideline, but it has one national patient-reported registry (RISA, FROM Bergamo; 82 pts; PMID 38930051). Because no centre qualifies on P1, Tier 1 rests on P3 national-cohort coordination: only Besta qualifies, as the FAST Italia AS Biobank lead plus REVEAL/Aurora site. Obudanersen's real Italian evidence base is the REVEAL/HALOS cluster at Besta, Pisa (Stella Maris/AOU Pisana), OPBG and Medea Conegliano. Competitor Aurora sites (Meyer, Gemelli, Besta) are in the same tier. A long tail of OR.S.A.-listed child-neuropsychiatry/epilepsy services and ERN ITHACA/EpiCARE HCPs makes up Tier 2–3.
A8: Spain | B8: =COUNTIFS(Country_Centres!$A$3:$A$97,$A8,Country_Centres!$B$3:$B$97,1) -> 0 | C8: =COUNTIFS(Country_Centres!$A$3:$A$97,$A8,Country_Centres!$B$3:$B$97,2) -> 5 | D8: =COUNTIFS(Country_Centres!$A$3:$A$97,$A8,Country_Centres!$B$3:$B$97,3) -> 12 | E8: =COUNTIFS(Country_Centres!$A$3:$A$97,$A8,Country_Centres!$B$3:$B$97,4) -> 0 | F8: =COUNTIF(Country_Centres!$A$3:$A$97,$A8) -> 17 | G8: Tier 4: not enumerated — not requested. Spain has two monographic AS units — Parc Taulí (Sabadell; ASF clinic; first Spanish REVEAL site) and Puerta de Hierro (Majadahonda; national AS natural-history coordinator) — plus SJD Barcelona (REVEAL site; ERN ITHACA+EpiCARE coordinator). No centre meets strict Tier 1 because there is no Spanish P1 guideline author and the two AS units are not ERN ITHACA/EpiCARE members; treat Parc Taulí and Puerta de Hierro as Tier-1-equivalent national anchors. Care is concentrated (chronic disease) — Tier 3 ERN/university hospitals matter mainly for referral and future IT-ASO capacity.
A9: United Kingdom | B9: =COUNTIFS(Country_Centres!$A$3:$A$97,$A9,Country_Centres!$B$3:$B$97,1) -> 1 | C9: =COUNTIFS(Country_Centres!$A$3:$A$97,$A9,Country_Centres!$B$3:$B$97,2) -> 4 | D9: =COUNTIFS(Country_Centres!$A$3:$A$97,$A9,Country_Centres!$B$3:$B$97,3) -> 11 | E9: =COUNTIFS(Country_Centres!$A$3:$A$97,$A9,Country_Centres!$B$3:$B$97,4) -> 0 | F9: =COUNTIF(Country_Centres!$A$3:$A$97,$A9) -> 16 | G9: Tier 4: not enumerated — not requested. After follow-up verification UK has one Tier 1 anchor — Oxford (ION582 HALOS+REVEAL site, ex-GTX-102 site, national natural-history coordinator) — with Manchester (UK's only specialist AS clinic, 2009 guideline lead, AS register) provisionally Tier 2 pending confirmation of 2021–2026 publications, alongside GOSH (REVEAL site), Cambridge (ex-GTX-102 site) and the Birmingham behaviour/sleep hub. P4 = N/A (post-Brexit); tiering uses national leadership, registry and trial signal. No UK KOL reaches Tier 1 by score.
A10: TOTAL (EU4+UK) | B10: =SUM(B5:B9) -> 8 | C10: =SUM(C5:C9) -> 28 | D10: =SUM(D5:D9) -> 59 | E10: =SUM(E5:E9) -> 0 | F10: =SUM(F5:F9) -> 95 | G10: ="Tier 4 not enumerated — not requested. Reconciles with Country_Centres row count: "&IF(F10=COUNTA(Country_Centres!$D$3:$D$97),"YES","NO — check") -> Tier 4 not enumerated — not requested. Reconciles with Country_Centres row count: YES
A12: B. KOLs × COUNTRY × TIER (KOL Tier for TOV, formula-driven from Total score)
A13: Country | B13: Tier 1 | C13: Tier 2 | D13: Tier 3 | E13: Total enumerated | F13: Notes
A14: France | B14: =COUNTIFS(KOL_Roster!$A$3:$A$99,$A14,KOL_Roster!$J$3:$J$99,1) -> 0 | C14: =COUNTIFS(KOL_Roster!$A$3:$A$99,$A14,KOL_Roster!$J$3:$J$99,2) -> 6 | D14: =COUNTIFS(KOL_Roster!$A$3:$A$99,$A14,KOL_Roster!$J$3:$J$99,3) -> 13 | E14: =COUNTIF(KOL_Roster!$A$3:$A$99,$A14) -> 19 | F14: 19 named KOLs (minimum 15 per country met). Highest total score 22/30 (Pr Rima Nabbout). No KOL reaches Tier 1 (24–30): publication/speaker scores use the evidence floor because live PubMed access was unavailable — re-score after a PubMed author sweep.
A15: Germany | B15: =COUNTIFS(KOL_Roster!$A$3:$A$99,$A15,KOL_Roster!$J$3:$J$99,1) -> 0 | C15: =COUNTIFS(KOL_Roster!$A$3:$A$99,$A15,KOL_Roster!$J$3:$J$99,2) -> 8 | D15: =COUNTIFS(KOL_Roster!$A$3:$A$99,$A15,KOL_Roster!$J$3:$J$99,3) -> 12 | E15: =COUNTIF(KOL_Roster!$A$3:$A$99,$A15) -> 20 | F15: 20 named KOLs (minimum 15 per country met). Highest total score 14/30 (Dr. rer. nat. Jasmin Beygo). No KOL reaches Tier 1 (24–30): publication/speaker scores use the evidence floor because live PubMed access was unavailable — re-score after a PubMed author sweep.
A16: Italy | B16: =COUNTIFS(KOL_Roster!$A$3:$A$99,$A16,KOL_Roster!$J$3:$J$99,1) -> 0 | C16: =COUNTIFS(KOL_Roster!$A$3:$A$99,$A16,KOL_Roster!$J$3:$J$99,2) -> 8 | D16: =COUNTIFS(KOL_Roster!$A$3:$A$99,$A16,KOL_Roster!$J$3:$J$99,3) -> 15 | E16: =COUNTIF(KOL_Roster!$A$3:$A$99,$A16) -> 23 | F16: 23 named KOLs (minimum 15 per country met). Highest total score 18/30 (Prof.ssa Roberta Battini). No KOL reaches Tier 1 (24–30): publication/speaker scores use the evidence floor because live PubMed access was unavailable — re-score after a PubMed author sweep.
A17: Spain | B17: =COUNTIFS(KOL_Roster!$A$3:$A$99,$A17,KOL_Roster!$J$3:$J$99,1) -> 0 | C17: =COUNTIFS(KOL_Roster!$A$3:$A$99,$A17,KOL_Roster!$J$3:$J$99,2) -> 6 | D17: =COUNTIFS(KOL_Roster!$A$3:$A$99,$A17,KOL_Roster!$J$3:$J$99,3) -> 12 | E17: =COUNTIF(KOL_Roster!$A$3:$A$99,$A17) -> 18 | F17: 18 named KOLs (minimum 15 per country met). Highest total score 20/30 (Dra. Ana Roche Martínez (MD, PhD; neuropaediatrician)). No KOL reaches Tier 1 (24–30): publication/speaker scores use the evidence floor because live PubMed access was unavailable — re-score after a PubMed author sweep.
A18: United Kingdom | B18: =COUNTIFS(KOL_Roster!$A$3:$A$99,$A18,KOL_Roster!$J$3:$J$99,1) -> 0 | C18: =COUNTIFS(KOL_Roster!$A$3:$A$99,$A18,KOL_Roster!$J$3:$J$99,2) -> 5 | D18: =COUNTIFS(KOL_Roster!$A$3:$A$99,$A18,KOL_Roster!$J$3:$J$99,3) -> 12 | E18: =COUNTIF(KOL_Roster!$A$3:$A$99,$A18) -> 17 | F18: 17 named KOLs (minimum 15 per country met). Highest total score 22/30 (Prof Jill Clayton-Smith). No KOL reaches Tier 1 (24–30): publication/speaker scores use the evidence floor because live PubMed access was unavailable — re-score after a PubMed author sweep. Only 8 of 17 named KOLs are physicians (see Verification_Flags).
A19: TOTAL (EU4+UK) | B19: =SUM(B14:B18) -> 0 | C19: =SUM(C14:C18) -> 33 | D19: =SUM(D14:D18) -> 64 | E19: =SUM(E14:E18) -> 97 | F19: ="Reconciles with KOL_Roster row count: "&IF(E19=COUNTA(KOL_Roster!$B$3:$B$99),"YES","NO — check") -> Reconciles with KOL_Roster row count: YES
A21: C. CROSS-CUTS — CENTRES (COUNTIF/COUNTIFS with wildcards on Country_Centres P-columns)
A22: Cross-cut (criterion) | B22: France | C22: Germany | D22: Italy | E22: Spain | F22: United Kingdom | G22: TOTAL (EU4+UK)
A23: Centres hosting a P1 guideline author (P1 starts "Yes") | B23: =COUNTIFS(Country_Centres!$A$3:$A$97,B$22,Country_Centres!$H$3:$H$97,"Yes*") -> 1 | C23: =COUNTIFS(Country_Centres!$A$3:$A$97,C$22,Country_Centres!$H$3:$H$97,"Yes*") -> 4 | D23: =COUNTIFS(Country_Centres!$A$3:$A$97,D$22,Country_Centres!$H$3:$H$97,"Yes*") -> 0 | E23: =COUNTIFS(Country_Centres!$A$3:$A$97,E$22,Country_Centres!$H$3:$H$97,"Yes*") -> 0 | F23: =COUNTIFS(Country_Centres!$A$3:$A$97,F$22,Country_Centres!$H$3:$H$97,"Yes*") -> 1 | G23: =SUM(B23:F23) -> 6
A24: Centres with P2 publication / trial authorship (P2 starts "Yes") | B24: =COUNTIFS(Country_Centres!$A$3:$A$97,B$22,Country_Centres!$I$3:$I$97,"Yes*") -> 3 | C24: =COUNTIFS(Country_Centres!$A$3:$A$97,C$22,Country_Centres!$I$3:$I$97,"Yes*") -> 4 | D24: =COUNTIFS(Country_Centres!$A$3:$A$97,D$22,Country_Centres!$I$3:$I$97,"Yes*") -> 7 | E24: =COUNTIFS(Country_Centres!$A$3:$A$97,E$22,Country_Centres!$I$3:$I$97,"Yes*") -> 5 | F24: =COUNTIFS(Country_Centres!$A$3:$A$97,F$22,Country_Centres!$I$3:$I$97,"Yes*") -> 6 | G24: =SUM(B24:F24) -> 25
A25: …of which with ION582 (obudanersen) trial signal (P2 "Yes" and contains "ION582") | B25: =COUNTIFS(Country_Centres!$A$3:$A$97,B$22,Country_Centres!$I$3:$I$97,"Yes*",Country_Centres!$I$3:$I$97,"*ION582*") -> 1 | C25: =COUNTIFS(Country_Centres!$A$3:$A$97,C$22,Country_Centres!$I$3:$I$97,"Yes*",Country_Centres!$I$3:$I$97,"*ION582*") -> 1 | D25: =COUNTIFS(Country_Centres!$A$3:$A$97,D$22,Country_Centres!$I$3:$I$97,"Yes*",Country_Centres!$I$3:$I$97,"*ION582*") -> 4 | E25: =COUNTIFS(Country_Centres!$A$3:$A$97,E$22,Country_Centres!$I$3:$I$97,"Yes*",Country_Centres!$I$3:$I$97,"*ION582*") -> 2 | F25: =COUNTIFS(Country_Centres!$A$3:$A$97,F$22,Country_Centres!$I$3:$I$97,"Yes*",Country_Centres!$I$3:$I$97,"*ION582*") -> 2 | G25: =SUM(B25:F25) -> 10
A26: …of which with competitor-trial signal (P2 "Yes" and contains competitor / apazunersen / GTX-102 / rugonersen / Aspire) | B26: {=SUMPRODUCT((Country_Centres!$A$3:$A$97=B$22)*(LEFT(Country_Centres!$I$3:$I$97,3)="Yes")*((ISNUMBER(SEARCH("competitor",Country_Centres!$I$3:$I$97))+ISNUMBER(SEARCH("apazunersen",Country_Centres!$I$3:$I$97))+ISNUMBER(SEARCH("GTX-102",Country_Centres!$I$3:$I$97))+ISNUMBER(SEARCH("rugonersen",Country_Centres!$I$3:$I$97))+ISNUMBER(SEARCH("Aspire",Country_Centres!$I$3:$I$97)))>0))} -> 2 | C26: {=SUMPRODUCT((Country_Centres!$A$3:$A$97=C$22)*(LEFT(Country_Centres!$I$3:$I$97,3)="Yes")*((ISNUMBER(SEARCH("competitor",Country_Centres!$I$3:$I$97))+ISNUMBER(SEARCH("apazunersen",Country_Centres!$I$3:$I$97))+ISNUMBER(SEARCH("GTX-102",Country_Centres!$I$3:$I$97))+ISNUMBER(SEARCH("rugonersen",Country_Centres!$I$3:$I$97))+ISNUMBER(SEARCH("Aspire",Country_Centres!$I$3:$I$97)))>0))} -> 3 | D26: {=SUMPRODUCT((Country_Centres!$A$3:$A$97=D$22)*(LEFT(Country_Centres!$I$3:$I$97,3)="Yes")*((ISNUMBER(SEARCH("competitor",Country_Centres!$I$3:$I$97))+ISNUMBER(SEARCH("apazunersen",Country_Centres!$I$3:$I$97))+ISNUMBER(SEARCH("GTX-102",Country_Centres!$I$3:$I$97))+ISNUMBER(SEARCH("rugonersen",Country_Centres!$I$3:$I$97))+ISNUMBER(SEARCH("Aspire",Country_Centres!$I$3:$I$97)))>0))} -> 3 | E26: {=SUMPRODUCT((Country_Centres!$A$3:$A$97=E$22)*(LEFT(Country_Centres!$I$3:$I$97,3)="Yes")*((ISNUMBER(SEARCH("competitor",Country_Centres!$I$3:$I$97))+ISNUMBER(SEARCH("apazunersen",Country_Centres!$I$3:$I$97))+ISNUMBER(SEARCH("GTX-102",Country_Centres!$I$3:$I$97))+ISNUMBER(SEARCH("rugonersen",Country_Centres!$I$3:$I$97))+ISNUMBER(SEARCH("Aspire",Country_Centres!$I$3:$I$97)))>0))} -> 5 | F26: {=SUMPRODUCT((Country_Centres!$A$3:$A$97=F$22)*(LEFT(Country_Centres!$I$3:$I$97,3)="Yes")*((ISNUMBER(SEARCH("competitor",Country_Centres!$I$3:$I$97))+ISNUMBER(SEARCH("apazunersen",Country_Centres!$I$3:$I$97))+ISNUMBER(SEARCH("GTX-102",Country_Centres!$I$3:$I$97))+ISNUMBER(SEARCH("rugonersen",Country_Centres!$I$3:$I$97))+ISNUMBER(SEARCH("Aspire",Country_Centres!$I$3:$I$97)))>0))} -> 3 | G26: =SUM(B26:F26) -> 16
A27: Centres with a P3 coordinator role (P3 contains "Coordinator") | B27: =COUNTIFS(Country_Centres!$A$3:$A$97,B$22,Country_Centres!$J$3:$J$97,"*Coordinator*") -> 1 | C27: =COUNTIFS(Country_Centres!$A$3:$A$97,C$22,Country_Centres!$J$3:$J$97,"*Coordinator*") -> 1 | D27: =COUNTIFS(Country_Centres!$A$3:$A$97,D$22,Country_Centres!$J$3:$J$97,"*Coordinator*") -> 2 | E27: =COUNTIFS(Country_Centres!$A$3:$A$97,E$22,Country_Centres!$J$3:$J$97,"*Coordinator*") -> 1 | F27: =COUNTIFS(Country_Centres!$A$3:$A$97,F$22,Country_Centres!$J$3:$J$97,"*Coordinator*") -> 2 | G27: =SUM(B27:F27) -> 7
A28: Centres listed as P3 sites (P3 contains "Site", excluding "No…" entries) | B28: =COUNTIFS(Country_Centres!$A$3:$A$97,B$22,Country_Centres!$J$3:$J$97,"*Site*",Country_Centres!$J$3:$J$97,"<>No*") -> 2 | C28: =COUNTIFS(Country_Centres!$A$3:$A$97,C$22,Country_Centres!$J$3:$J$97,"*Site*",Country_Centres!$J$3:$J$97,"<>No*") -> 3 | D28: =COUNTIFS(Country_Centres!$A$3:$A$97,D$22,Country_Centres!$J$3:$J$97,"*Site*",Country_Centres!$J$3:$J$97,"<>No*") -> 6 | E28: =COUNTIFS(Country_Centres!$A$3:$A$97,E$22,Country_Centres!$J$3:$J$97,"*Site*",Country_Centres!$J$3:$J$97,"<>No*") -> 5 | F28: =COUNTIFS(Country_Centres!$A$3:$A$97,F$22,Country_Centres!$J$3:$J$97,"*Site*",Country_Centres!$J$3:$J$97,"<>No*") -> 4 | G28: =SUM(B28:F28) -> 20
A29: Centres that are P4 ERN ITHACA / EpiCARE HCPs (P4 starts "Yes") | B29: =COUNTIFS(Country_Centres!$A$3:$A$97,B$22,Country_Centres!$K$3:$K$97,"Yes*") -> 6 | C29: =COUNTIFS(Country_Centres!$A$3:$A$97,C$22,Country_Centres!$K$3:$K$97,"Yes*") -> 12 | D29: =COUNTIFS(Country_Centres!$A$3:$A$97,D$22,Country_Centres!$K$3:$K$97,"Yes*") -> 16 | E29: =COUNTIFS(Country_Centres!$A$3:$A$97,E$22,Country_Centres!$K$3:$K$97,"Yes*") -> 6 | F29: =COUNTIFS(Country_Centres!$A$3:$A$97,F$22,Country_Centres!$K$3:$K$97,"Yes*") -> 0 | G29: =SUM(B29:F29) -> 40
A30: Centres with an explicit P5 Angelman programme (P5 = "Yes*") | B30: =COUNTIFS(Country_Centres!$A$3:$A$97,B$22,Country_Centres!$L$3:$L$97,"Yes*") -> 3 | C30: =COUNTIFS(Country_Centres!$A$3:$A$97,C$22,Country_Centres!$L$3:$L$97,"Yes*") -> 3 | D30: =COUNTIFS(Country_Centres!$A$3:$A$97,D$22,Country_Centres!$L$3:$L$97,"Yes*") -> 18 | E30: =COUNTIFS(Country_Centres!$A$3:$A$97,E$22,Country_Centres!$L$3:$L$97,"Yes*") -> 2 | F30: =COUNTIFS(Country_Centres!$A$3:$A$97,F$22,Country_Centres!$L$3:$L$97,"Yes*") -> 1 | G30: =SUM(B30:F30) -> 27
A32: D. CROSS-CUTS — KOLs (COUNTIFS / SUMPRODUCT on KOL_Roster score and signal columns)
A33: Cross-cut (criterion) | B33: France | C33: Germany | D33: Italy | E33: Spain | F33: United Kingdom | G33: TOTAL (EU4+UK)
A34: KOLs with guideline publications (Guideline score ≥3 OR P1 column starts "Yes") | B34: {=SUMPRODUCT((KOL_Roster!$A$3:$A$99=B$33)*(((KOL_Roster!$K$3:$K$99>=3)+(LEFT(KOL_Roster!$E$3:$E$99,3)="Yes"))>0))} -> 1 | C34: {=SUMPRODUCT((KOL_Roster!$A$3:$A$99=C$33)*(((KOL_Roster!$K$3:$K$99>=3)+(LEFT(KOL_Roster!$E$3:$E$99,3)="Yes"))>0))} -> 3 | D34: {=SUMPRODUCT((KOL_Roster!$A$3:$A$99=D$33)*(((KOL_Roster!$K$3:$K$99>=3)+(LEFT(KOL_Roster!$E$3:$E$99,3)="Yes"))>0))} -> 0 | E34: {=SUMPRODUCT((KOL_Roster!$A$3:$A$99=E$33)*(((KOL_Roster!$K$3:$K$99>=3)+(LEFT(KOL_Roster!$E$3:$E$99,3)="Yes"))>0))} -> 1 | F34: {=SUMPRODUCT((KOL_Roster!$A$3:$A$99=F$33)*(((KOL_Roster!$K$3:$K$99>=3)+(LEFT(KOL_Roster!$E$3:$E$99,3)="Yes"))>0))} -> 1 | G34: =SUM(B34:F34) -> 6
A35: KOLs with clinical-trial roles (Clinical-trials score ≥3) | B35: =COUNTIFS(KOL_Roster!$A$3:$A$99,B$33,KOL_Roster!$M$3:$M$99,">=3") -> 3 | C35: =COUNTIFS(KOL_Roster!$A$3:$A$99,C$33,KOL_Roster!$M$3:$M$99,">=3") -> 2 | D35: =COUNTIFS(KOL_Roster!$A$3:$A$99,D$33,KOL_Roster!$M$3:$M$99,">=3") -> 6 | E35: =COUNTIFS(KOL_Roster!$A$3:$A$99,E$33,KOL_Roster!$M$3:$M$99,">=3") -> 4 | F35: =COUNTIFS(KOL_Roster!$A$3:$A$99,F$33,KOL_Roster!$M$3:$M$99,">=3") -> 2 | G35: =SUM(B35:F35) -> 17
A36: KOLs with disease publications (Publications score ≥3) | B36: =COUNTIFS(KOL_Roster!$A$3:$A$99,B$33,KOL_Roster!$L$3:$L$99,">=3") -> 1 | C36: =COUNTIFS(KOL_Roster!$A$3:$A$99,C$33,KOL_Roster!$L$3:$L$99,">=3") -> 2 | D36: =COUNTIFS(KOL_Roster!$A$3:$A$99,D$33,KOL_Roster!$L$3:$L$99,">=3") -> 7 | E36: =COUNTIFS(KOL_Roster!$A$3:$A$99,E$33,KOL_Roster!$L$3:$L$99,">=3") -> 7 | F36: =COUNTIFS(KOL_Roster!$A$3:$A$99,F$33,KOL_Roster!$L$3:$L$99,">=3") -> 8 | G36: =SUM(B36:F36) -> 25
A37: KOLs with an international presentation / meeting signal (column not blank, not "No…/None…/Not…", not "international … not verified") | B37: =COUNTIFS(KOL_Roster!$A$3:$A$99,B$33,KOL_Roster!$H$3:$H$99,"<>",KOL_Roster!$H$3:$H$99,"<>No*",KOL_Roster!$H$3:$H$99,"<>*international not verified*",KOL_Roster!$H$3:$H$99,"<>*international oral not verified*") -> 2 | C37: =COUNTIFS(KOL_Roster!$A$3:$A$99,C$33,KOL_Roster!$H$3:$H$99,"<>",KOL_Roster!$H$3:$H$99,"<>No*",KOL_Roster!$H$3:$H$99,"<>*international not verified*",KOL_Roster!$H$3:$H$99,"<>*international oral not verified*") -> 0 | D37: =COUNTIFS(KOL_Roster!$A$3:$A$99,D$33,KOL_Roster!$H$3:$H$99,"<>",KOL_Roster!$H$3:$H$99,"<>No*",KOL_Roster!$H$3:$H$99,"<>*international not verified*",KOL_Roster!$H$3:$H$99,"<>*international oral not verified*") -> 0 | E37: =COUNTIFS(KOL_Roster!$A$3:$A$99,E$33,KOL_Roster!$H$3:$H$99,"<>",KOL_Roster!$H$3:$H$99,"<>No*",KOL_Roster!$H$3:$H$99,"<>*international not verified*",KOL_Roster!$H$3:$H$99,"<>*international oral not verified*") -> 3 | F37: =COUNTIFS(KOL_Roster!$A$3:$A$99,F$33,KOL_Roster!$H$3:$H$99,"<>",KOL_Roster!$H$3:$H$99,"<>No*",KOL_Roster!$H$3:$H$99,"<>*international not verified*",KOL_Roster!$H$3:$H$99,"<>*international oral not verified*") -> 0 | G37: =SUM(B37:F37) -> 5
A38: KOLs flagged as competitor-trial investigators (Engagement priority contains "competitor") | B38: =COUNTIFS(KOL_Roster!$A$3:$A$99,B$33,KOL_Roster!$I$3:$I$99,"*competitor*") -> 2 | C38: =COUNTIFS(KOL_Roster!$A$3:$A$99,C$33,KOL_Roster!$I$3:$I$99,"*competitor*") -> 2 | D38: =COUNTIFS(KOL_Roster!$A$3:$A$99,D$33,KOL_Roster!$I$3:$I$99,"*competitor*") -> 3 | E38: =COUNTIFS(KOL_Roster!$A$3:$A$99,E$33,KOL_Roster!$I$3:$I$99,"*competitor*") -> 2 | F38: =COUNTIFS(KOL_Roster!$A$3:$A$99,F$33,KOL_Roster!$I$3:$I$99,"*competitor*") -> 1 | G38: =SUM(B38:F38) -> 10

Sheet Infrastructure
A1: Infrastructure — Angelman syndrome diagnostic, assessment & treatment requirements mapped to centre tiers (incl. obudanersen IT-ASO overlay)
A2: Domain | B2: Capability | C2: Minimum requirement | D2: Typical Tier 1-2 coverage | E2: Notes / failure modes
A3: DIAGNOSTICS
A4: Diagnostics | B4: Methylation analysis of 15q11.2-q13 (MS-MLPA / methylation-specific PCR) | C4: Access to accredited genetics lab offering MS-MLPA; detects deletion, UPD and imprinting defects | D4: Universal at Tier 1-2 (in-house or regional genetics lab) | E4: Normal methylation does not exclude AS (UBE3A variants); failure mode = stopping work-up after normal methylation.
A5: Diagnostics | B5: Deletion sizing (class I vs II) / CMA; UPD studies (parental microsatellite/SNP); imprinting-centre analysis | C5: CMA + parental samples; IC deletion testing for recurrence counselling | D5: Tier 1 routine; Tier 2 variable (send-out) | E5: Genotype matters: deletion = most severe phenotype (Bindels-de Heus 2020); UPD/ID distinction needed for CHAMPION eligibility (central or qualified local geneticist confirmation).
A6: Diagnostics | B6: UBE3A sequencing (NGS panel/exome) for methylation-normal cases | C6: Clinical NGS with UBE3A coverage + variant interpretation | D6: Tier 1-2 via clinical genetics | E6: Minority genotype; REVEAL includes UBE3A mutation; Aspire excluded it (deletion only).
A7: Diagnostics | B7: Genetic-subtype gating of trial/treatment eligibility | C7: Documented molecular genotype in record | D7: Tier 1-2 hold genotype; older adults often undocumented | E7: REVEAL = deletion or UBE3A mutation only; CHAMPION = UPD/ID only. Undocumented genotype in adults/legacy diagnoses is the main screen-failure driver → re-testing capacity required.
A8: Diagnostics | B8: Clinical diagnosis per Williams 2006 consensus criteria; EEG pattern | C8: Clinician familiar with consistent/frequent/associated features; paediatric EEG | D8: Universal at Tier 1-2 | E8: Characteristic EEG (high-amplitude rhythmic delta) supports diagnosis; misdiagnosis as autism/CP delays testing (Mertz 2013: later diagnosis in non-deletion).
A9: SEVERITY ASSESSMENT
A10: Severity assessment | B10: Bayley-4 (cognition, receptive/expressive communication, gross/fine motor) | C10: Trained psychologist/rater; standardised administration | D10: Tier 1 research centres; Tier 2 limited | E10: REVEAL primary endpoint = Bayley-4 expressive communication; Aspire primary = Bayley-4 cognition. Rater training/reliability a key operational risk (Aspire failed on Bayley-4 cognition).
A11: Severity assessment | B11: Vineland-3 adaptive behaviour | C11: Caregiver interview by trained rater | D11: Tier 1 routine in research; Tier 2 variable | E11: Used in HALOS and Aspire secondaries; language-validated versions needed per country.
A12: Severity assessment | B12: AS-specific global scales (SAS-CGI-S/C, CGI-I-AS) and Angelman Severity Assessment (ASA) | C12: Clinician trained on AS-anchored CGI | D12: Trial sites only | E12: SAS-CGI-C drove HALOS headline (97%); gaboxadol failed on CGI-I-AS — scale sensitivity/placebo response caveat.
A13: Severity assessment | B13: Observer-Reported Communication Ability (ORCA) & caregiver PROs | C13: eCOA/caregiver-report infrastructure | D13: Trial sites | E13: ORCA used in HALOS; translation/cultural validation for EU languages.
A14: Severity assessment | B14: Sleep assessment (diaries, actigraphy) and seizure diaries | C14: Sleep clinic / actigraphy; structured seizure diary | D14: Tier 1 neuropaediatrics/sleep services | E14: Sleep and seizures are top caregiver burdens; prerequisite for stable baseline (REVEAL requires ≥8 weeks stable concomitant meds).
A15: Severity assessment | B15: Quantitative EEG delta-power biomarker | C15: Research-grade EEG acquisition + central quantitative analysis | D15: Tier 1 research centres | E15: HALOS reported reduction in slow-wave delta activity; rugonersen showed partial EEG normalisation; not yet a validated surrogate.
A16: TREATMENT
A17: Treatment (SoC) | B17: Anti-seizure medication management incl. NCSE recognition | C17: Paediatric epileptologist; EEG/video-EEG | D17: Tier 1-2 (EpiCARE HCPs) | E17: High NCSE rate in AS (Bindels-de Heus 2020); ASM selection per Duis 2022 neurology section.
A18: Treatment (SoC) | B18: Sleep management, behaviour, GI/feeding, orthopaedics | C18: Multidisciplinary clinic (Duis 2022 consensus domains) | D18: Tier 1 full MDT; Tier 2 partial | E18: Duis 2022 consensus covers genetics, neurology, sleep, psychiatry, orthopaedics, ophthalmology, communication, therapies, caregiver health.
A19: Treatment (SoC) | B19: AAC / communication therapy; PT/OT | C19: Speech & language therapist with AAC expertise; PT/OT | D19: Variable — often community-based | E19: Expressive communication is REVEAL primary endpoint → AAC-competent SLT input is both SoC and endpoint-relevant.
A20: Treatment — MOST DIFFERENTIATING | B20: Repeat intrathecal ASO administration via lumbar puncture in a non-verbal, often uncooperative paediatric AND adult population | C20: Paediatric day-unit or procedural suite; procedural sedation/GA without intubation (REVEAL/CHAMPION criterion); anaesthesia team experienced with ID/behaviour; imaging (fluoroscopy/US) for difficult spines; CSF sampling; post-LP monitoring; pharmacy handling of IT product | D20: Nusinersen-experienced paediatric neurology / SMA centres (Tier 1-2) — but adult AS administration capacity is thin | E20: Scoliosis/spinal anatomy, obesity/hyperphagia, behavioural distress and seizures complicate LP; Ionis required each REVEAL site to self-certify capability for Cohort 1, Cohort 2 or both — adult-capable sites are fewer. EU sham-skin-prick control still requires full procedural set-up. Lifelong quarterly IT dosing = chronic procedural load.
A21: Treatment — benchmark | B21: Nusinersen (SPINRAZA) IT delivery footprint | C21: Doctor/nurse experienced in IT injection; sedation as needed (EMA EPAR) | D21: Established at SMA treatment centres across EU4+UK since 2017 | E21: Same Ionis IT-ASO paradigm; SMA centres already run repeat-LP lists, sedation pathways and difficult-spine imaging — directly transferable, though SMA vs AS behaviour/anaesthesia profiles differ.
A22: REHABILITATION / CHRONIC MANAGEMENT
A23: Rehabilitation / chronic management | B23: Multidisciplinary AS clinic (paediatric) | C23: Named AS/ID clinic with genetics, neurology, behaviour, sleep, therapies | D23: Tier 1 (e.g. national expertise centres; ASF International Clinic Network partner Erasmus MC in NL) | E23: Few dedicated AS clinics in EU4+UK; most care in broader ID/neurogenetics/epilepsy programmes (P5 'Partial').
A24: Rehabilitation / chronic management | B24: Transition to adult care | C24: Adult neurology/ID service accepting AS; transition protocol | D24: Weak across EU4+UK | E24: REVEAL Cohort 2 (18–50 y) and any label covering adults require adult LP/sedation capacity — major gap.
A25: FUTURE-STATE — ASSET OVERLAY (obudanersen)
A26: Future-state (a) | B26: Obudanersen administration capability & infrastructure argument | C26: IT-ASO-ready site: procedural sedation, LP list capacity every ~12 weeks, genotype-confirmed cohort | D26: Nusinersen-experienced paediatric neurology centres = ready-made IT-ASO footprint; addressable centre base ≈ SMA treatment centres + AS/ID expertise centres | E26: Obudanersen is infrastructure-HEAVIER than oral SoC (ASMs, sleep meds) but uses an existing, reimbursed IT-ASO pathway (nusinersen/tofersen); no loading regimen (quarterly from start) vs nusinersen loading — lighter than SMA initiation. Positioning: 'plug into SMA IT infrastructure, add AS expertise'.
A27: Future-state (b) | B27: RWE-registry participation | C27: Consent + data entry capacity for Global AS Registry, LADDER (ASF International Clinic Network/Erasmus, from Jan-2026), national registries (e.g. Italian RISA registry, FROM Bergamo) | D27: Tier 1 participate; Tier 2 sporadic | E27: Post-approval RWE/managed-access will require structured outcome capture (Bayley-4/Vineland/ORCA) — few EU centres have dedicated research coordinators for AS.
A28: Future-state (c) | B28: Trial-readiness after Aspire failure | C28: Sites with prior UBE3A-ATS ASO experience (GTX-102/Aspire/TANGELO) and trained raters | D28: ES (Parc Taulí, SJD, Puerta de Hierro, Virgen del Rocío), DE (UKE, Leipzig, LMU), UK (GOSH, Oxford, Cambridge), FR (Necker, Timone) | E28: Ex-Aspire sites have idle IT-ASO capacity and trained raters → high-value for CHAMPION EU expansion / REVEAL LTE / early access; but family & investigator sentiment post-Aspire must be managed.

Sheet Sources_Caveats
A1: Sources_Caveats — authoritative sources (150, de-duplicated; every URL clickable) + caveats + asset & competitor trial footprint
A2: Authoritative source | B2: URL / reference | C2: What it provides
A3: Duis J et al. A multidisciplinary approach and consensus statement to establish standards of care for Angelman syndrome. Mol Genet Genomic Med 2022;10(3):e1843. doi:10.1002/mgg3.1843; PMID 35150089; PMCID PMC8922964 | B3: =HYPERLINK("https://europepmc.org/articles/PMC8922964/","https://europepmc.org/articles/PMC8922964/") -> https://europepmc.org/articles/PMC8922964/ | C3: P1 international consensus standards of care; author list (US + NL/BE/AU/CA)
A4: HAS / CRMR Déficiences intellectuelles de causes rares. PNDS Syndrome d'Angelman (online 1-Dec-2021) | B4: =HYPERLINK("https://www.has-sante.fr/jcms/p_3300847/fr/syndrome-d-angelman","https://www.has-sante.fr/jcms/p_3300847/fr/syndrome-d-angelman") -> https://www.has-sante.fr/jcms/p_3300847/fr/syndrome-d-angelman | C4: P1 French national guideline (PNDS, synthèse, argumentaire)
A5: Williams CA et al. Angelman syndrome 2005: updated consensus for diagnostic criteria. Am J Med Genet A 2006;140(5):413-418. doi:10.1002/ajmg.a.31074; PMID 16470747 | B5: =HYPERLINK("https://europepmc.org/article/MED/16470747","https://europepmc.org/article/MED/16470747") -> https://europepmc.org/article/MED/16470747 | C5: Clinical diagnostic criteria; EU co-authors (Clayton-Smith UK, Moncla FR, Laan NL, Kyllerman SE)
A6: Mertz LGB et al. Angelman syndrome in Denmark: birth incidence, genetic findings, and age at diagnosis. Am J Med Genet A 2013;161A(9):2197-2203. doi:10.1002/ajmg.a.36058; PMID 23913711 | B6: =HYPERLINK("https://research.regionh.dk/en/publications/angelman-syndrome-in-denmark-birth-incidence-genetic-findings-and/","https://research.regionh.dk/en/publications/angelman-syndrome-in-denmark-birth-incidence-genetic-findings-and/") -> https://research.regionh.dk/en/publications/angelman-syndrome-in-denmark-birth-incidence-genetic-findings-and/ | C6: European epidemiology: birth incidence 1:24,580; genotype split; age at diagnosis
A7: Bindels-de Heus KGCB et al. An overview of health issues and development in a large clinical cohort of children with Angelman syndrome. Am J Med Genet A 2020;182(1):53-63. doi:10.1002/ajmg.a.61382; PMID 31729827 | B7: =HYPERLINK("https://pmc.ncbi.nlm.nih.gov/articles/PMC6916553/","https://pmc.ncbi.nlm.nih.gov/articles/PMC6916553/") -> https://pmc.ncbi.nlm.nih.gov/articles/PMC6916553/ | C7: European natural-history cohort (ENCORE, Erasmus MC; n=100); NCSE, crouch gait, genotype–phenotype
A8: Keute M et al. Angelman syndrome genotypes manifest varying degrees of clinical severity and developmental impairment. Mol Psychiatry 2021;26(7):3625-3633 (DOI listed on Ionis obudanersen publications page) | B8: =HYPERLINK("https://ionis.com/taxonomy/term/566","https://ionis.com/taxonomy/term/566") -> https://ionis.com/taxonomy/term/566 | C8: Genotype severity (listed in Ionis obudanersen publications page)
A9: ClinicalTrials.gov NCT06914609 — REVEAL Phase 3 obudanersen (EU CT 2024-519711-33-00) | B9: =HYPERLINK("https://clinicaltrials.gov/study/NCT06914609","https://clinicaltrials.gov/study/NCT06914609") -> https://clinicaltrials.gov/study/NCT06914609 | C9: Design, 80 mg arm, cohorts, status, 41 locations incl. EU4+UK
A10: ClinicalTrials.gov NCT05127226 — HALOS Phase 1/2 ION582 | B10: =HYPERLINK("https://clinicaltrials.gov/study/NCT05127226","https://clinicaltrials.gov/study/NCT05127226") -> https://clinicaltrials.gov/study/NCT05127226 | C10: Phase 1/2 design and sites (mirror: eichor.com/study/NCT05127226)
A11: ClinicalTrials.gov NCT07782827 — CHAMPION Phase 3 (UPD/ID) | B11: =HYPERLINK("https://clinicaltrials.gov/study/NCT07782827","https://clinicaltrials.gov/study/NCT07782827") -> https://clinicaltrials.gov/study/NCT07782827 | C11: Open-label single-arm UPD/ID study; status; sites (mirror eichor.com)
A12: Ionis PR 6-Jul-2026: completes enrollment in pivotal cohort of REVEAL | B12: =HYPERLINK("https://ir.ionis.com/news-releases/news-release-details/ionis-completes-enrollment-pivotal-cohort-phase-3-reveal-study","https://ir.ionis.com/news-releases/news-release-details/ionis-completes-enrollment-pivotal-cohort-phase-3-reveal-study") -> https://ir.ionis.com/news-releases/news-release-details/ionis-completes-enrollment-pivotal-cohort-phase-3-reveal-study | C12: 136 pts Cohort 1; adult cohort Q3-2026; topline 2H-2027; designations
A13: Ionis PR 6-Nov-2024: pivotal Phase 3 trial design for ION582 | B13: =HYPERLINK("https://ir.ionis.com/news-releases/news-release-details/ionis-announces-pivotal-phase-3-trial-design-ion582-angelman","https://ir.ionis.com/news-releases/news-release-details/ionis-announces-pivotal-phase-3-trial-design-ion582-angelman") -> https://ir.ionis.com/news-releases/news-release-details/ionis-announces-pivotal-phase-3-trial-design-ion582-angelman | C13: Primary endpoint Bayley-4 expressive communication; quarterly dosing without loading
A14: Ionis PR 16-May-2024: positive topline HALOS | B14: =HYPERLINK("https://ir.ionis.com/news-releases/news-release-details/ionis-announces-positive-topline-results-phase-12a-trial-ion582","https://ir.ionis.com/news-releases/news-release-details/ionis-announces-positive-topline-results-phase-12a-trial-ion582") -> https://ir.ionis.com/news-releases/news-release-details/ionis-announces-positive-topline-results-phase-12a-trial-ion582 | C14: HALOS topline; Biogen opt-out; EEG delta reduction
A15: Ionis PR 22-Jul-2024: detailed HALOS results (BioSpace mirror) | B15: =HYPERLINK("https://www.biospace.com/ionis-announces-positive-detailed-results-from-the-halos-study-of-ion582-in-people-with-angelman-syndrome","https://www.biospace.com/ionis-announces-positive-detailed-results-from-the-halos-study-of-ion582-in-people-with-angelman-syndrome") -> https://www.biospace.com/ionis-announces-positive-detailed-results-from-the-halos-study-of-ion582-in-people-with-angelman-syndrome | C15: 51 pts; SAS-CGI-C 97%; Lynne Bird quote
A16: Ionis PR 11-Jun-2025: first patient dosed in REVEAL | B16: =HYPERLINK("https://ir.ionis.com/news-releases/news-release-details/first-patient-dosed-pivotal-phase-3-reveal-clinical-study-ion582","https://ir.ionis.com/news-releases/news-release-details/first-patient-dosed-pivotal-phase-3-reveal-clinical-study-ion582") -> https://ir.ionis.com/news-releases/news-release-details/first-patient-dosed-pivotal-phase-3-reveal-clinical-study-ion582 | C16: REVEAL start; designations
A17: Ionis community letter Apr-2026: first EU REVEAL sites (via ASF) | B17: =HYPERLINK("https://angelman.org/wp-content/uploads/2026/04/Ionis-REVEAL-sites-EU_community-letter.pdf","https://angelman.org/wp-content/uploads/2026/04/Ionis-REVEAL-sites-EU_community-letter.pdf") -> https://angelman.org/wp-content/uploads/2026/04/Ionis-REVEAL-sites-EU_community-letter.pdf | C17: LMU München + Parc Taulí; planned DE/IT/PL/ES; EU skin-prick sham
A18: Ionis community letter Jul-2026 (via ASF) | B18: =HYPERLINK("https://angelman.org/wp-content/uploads/2026/07/Ionis-update-REVEAL-July2026.pdf","https://angelman.org/wp-content/uploads/2026/07/Ionis-update-REVEAL-July2026.pdf") -> https://angelman.org/wp-content/uploads/2026/07/Ionis-update-REVEAL-July2026.pdf | C18: Cohort 1 complete; site cohort capability; CHAMPION timing
A19: Ionis community letter Dec-2025 (via ASF) | B19: =HYPERLINK("https://angelman.org/wp-content/uploads/2025/12/Community-Update-ION582-Ionis_Dec-2025.pdf","https://angelman.org/wp-content/uploads/2025/12/Community-Update-ION582-Ionis_Dec-2025.pdf") -> https://angelman.org/wp-content/uploads/2025/12/Community-Update-ION582-Ionis_Dec-2025.pdf | C19: 80 mg focus; CHAMPION announced; advocacy engagement
A20: Ionis Italy community statement May-2026 (via ORSA) | B20: =HYPERLINK("https://sindromediangelman.org/wp-content/uploads/2026/05/PA-IT-AS-260001-Community-Statement-REVEAL-Opens-in-Italy-052626.pdf","https://sindromediangelman.org/wp-content/uploads/2026/05/PA-IT-AS-260001-Community-Statement-REVEAL-Opens-in-Italy-052626.pdf") -> https://sindromediangelman.org/wp-content/uploads/2026/05/PA-IT-AS-260001-Community-Statement-REVEAL-Opens-in-Italy-052626.pdf | C20: Italian REVEAL sites: Besta, AOU Pisana, OPBG
A21: IRCCS Fondazione Stella Maris press release 21-May-2026 | B21: =HYPERLINK("https://www.fsm.unipi.it/2026/05/21/angelman-trial-clinico-ionis-pisa-2026/","https://www.fsm.unipi.it/2026/05/21/angelman-trial-clinico-ionis-pisa-2026/") -> https://www.fsm.unipi.it/2026/05/21/angelman-trial-clinico-ionis-pisa-2026/ | C21: Named Italian REVEAL investigators/centres (D'Arrigo, Battini, Danieli, Pietrafusa)
A22: Ionis HALOS program update slides (Crean & Bird, ASF 2024) | B22: =HYPERLINK("https://ionis.com/sites/default/files/2026-06/Crean%20Bird%20-%20HALOS%20-%20Angelman%20Syndrome%20Program%20Update.pdf","https://ionis.com/sites/default/files/2026-06/Crean%20Bird%20-%20HALOS%20-%20Angelman%20Syndrome%20Program%20Update.pdf") -> https://ionis.com/sites/default/files/2026-06/Crean%20Bird%20-%20HALOS%20-%20Angelman%20Syndrome%20Program%20Update.pdf | C22: HALOS MAD data; investigator disclosures
A23: EMA orphan designation EU/3/22/2636 (obudanersen) | B23: =HYPERLINK("https://www.ema.europa.eu/en/medicines/human/orphan-designations/eu-3-22-2636","https://www.ema.europa.eu/en/medicines/human/orphan-designations/eu-3-22-2636") -> https://www.ema.europa.eu/en/medicines/human/orphan-designations/eu-3-22-2636 | C23: EU orphan designation 21-Jun-2022, sponsor Ionis Development (Ireland)
A24: EMA EPAR Spinraza (nusinersen) | B24: =HYPERLINK("https://www.ema.europa.eu/en/medicines/human/EPAR/spinraza","https://www.ema.europa.eu/en/medicines/human/EPAR/spinraza") -> https://www.ema.europa.eu/en/medicines/human/EPAR/spinraza | C24: IT-ASO benchmark: IT injection by experienced staff; sedation may be needed
A25: ClinicalTrials.gov NCT06617429 — Aspire Phase 3 apazunersen | B25: =HYPERLINK("https://clinicaltrials.gov/study/NCT06617429","https://clinicaltrials.gov/study/NCT06617429") -> https://clinicaltrials.gov/study/NCT06617429 | C25: Design (sham-LP; Bayley-4 cognition primary); EU sites (mirror eichor.com)
A26: ClinicalTrials.gov NCT04259281 — GTX-102 Phase 1/2 | B26: =HYPERLINK("https://clinicaltrials.gov/study/NCT04259281","https://clinicaltrials.gov/study/NCT04259281") -> https://clinicaltrials.gov/study/NCT04259281 | C26: 25 sites incl. FR/DE/ES/UK
A27: Ultragenyx PR 2-Sep-2026: Phase 3 Aspire results | B27: =HYPERLINK("https://ir.ultragenyx.com/news-releases/news-release-details/ultragenyx-announces-phase-3-aspire-results-angelman-syndrome","https://ir.ultragenyx.com/news-releases/news-release-details/ultragenyx-announces-phase-3-aspire-results-angelman-syndrome") -> https://ir.ultragenyx.com/news-releases/news-release-details/ultragenyx-announces-phase-3-aspire-results-angelman-syndrome | C27: Aspire missed primary and key secondary endpoints
A28: Ultragenyx GTX-102 pipeline page | B28: =HYPERLINK("https://www.ultragenyx.com/our-research/pipeline/gtx-102-for-angelman-syndrome/","https://www.ultragenyx.com/our-research/pipeline/gtx-102-for-angelman-syndrome/") -> https://www.ultragenyx.com/our-research/pipeline/gtx-102-for-angelman-syndrome/ | C28: Designations incl. EMA PRIME; Aurora study
A29: Dindot SV et al. Sci Transl Med 2023;15:eabf4077. doi:10.1126/scitranslmed.abf4077; PMID 36947593 | B29: =HYPERLINK("https://pubmed.ncbi.nlm.nih.gov/36947593/","https://pubmed.ncbi.nlm.nih.gov/36947593/") -> https://pubmed.ncbi.nlm.nih.gov/36947593/ | C29: GTX-102 preclinical basis
A30: Rugonersen TANGELO Phase 1. Nature Medicine 2025. doi:10.1038/s41591-025-03784-7 | B30: =HYPERLINK("https://www.nature.com/articles/s41591-025-03784-7","https://www.nature.com/articles/s41591-025-03784-7") -> https://www.nature.com/articles/s41591-025-03784-7 | C30: Competitor UBE3A-ATS ASO publication
A31: Roche ForPatients — TANGELO site list | B31: =HYPERLINK("https://forpatients.roche.com/en/trials/neurodevelopmental-disorder/angelman-syndrome/a-study-to-investigate-the-safety--tolerability--pharma-19556.html","https://forpatients.roche.com/en/trials/neurodevelopmental-disorder/angelman-syndrome/a-study-to-investigate-the-safety--tolerability--pharma-19556.html") -> https://forpatients.roche.com/en/trials/neurodevelopmental-disorder/angelman-syndrome/a-study-to-investigate-the-safety--tolerability--pharma-19556.html | C31: Rugonersen EU sites (ES, IT, NL)
A32: Keary C et al. Gaboxadol in Angelman syndrome Phase 3. Eur J Paediatr Neurol 2023;47:6-12. doi:10.1016/j.ejpn.2023.07.008; PMID 37639777 | B32: =HYPERLINK("https://pubmed.ncbi.nlm.nih.gov/37639777/","https://pubmed.ncbi.nlm.nih.gov/37639777/") -> https://pubmed.ncbi.nlm.nih.gov/37639777/ | C32: NEPTUNE failure (NCT04106557)
A33: Neuren — NNZ-2591 Angelman programme | B33: =HYPERLINK("https://neurenpharma.com/angelman-syndrome","https://neurenpharma.com/angelman-syndrome") -> https://neurenpharma.com/angelman-syndrome | C33: Phase 2 AS top-line; designations
A34: MavriX Bio PR — first patient dosed ASCEND-AS (MVX-220, NCT07181837) | B34: =HYPERLINK("https://www.biospace.com/press-releases/mavrix-bio-announces-first-patient-dosed-in-ascend-as-trial-of-mvx-220-investigational-gene-therapy-for-angelman-syndrome","https://www.biospace.com/press-releases/mavrix-bio-announces-first-patient-dosed-in-ascend-as-trial-of-mvx-220-investigational-gene-therapy-for-angelman-syndrome") -> https://www.biospace.com/press-releases/mavrix-bio-announces-first-patient-dosed-in-ascend-as-trial-of-mvx-220-investigational-gene-therapy-for-angelman-syndrome | C34: First AAV gene therapy trial in AS
A35: Global Angelman Syndrome Registry | B35: =HYPERLINK("https://www.angelmanregistry.info/","https://www.angelmanregistry.info/") -> https://www.angelmanregistry.info/ | C35: P3 global caregiver-reported registry (FAST Australia origin)
A36: ASF International Clinic Network announcement (9-Jan-2026) | B36: =HYPERLINK("https://angelman.org/news-blog/international-clinic-network/","https://angelman.org/news-blog/international-clinic-network/") -> https://angelman.org/news-blog/international-clinic-network/ | C36: Erasmus Angelman Clinic partnership; LADDER-format data collection in Europe
A37: LADDER (Linking Angelman and Dup15q Data for Expanded Research), RTI | B37: =HYPERLINK("https://laddertotreatment.org/","https://laddertotreatment.org/") -> https://laddertotreatment.org/ | C37: P3 linked clinical/registry database
A38: ERN ITHACA — EU expert centres | B38: =HYPERLINK("https://ern-ithaca.eu/about-us/expert-centers/","https://ern-ithaca.eu/about-us/expert-centers/") -> https://ern-ithaca.eu/about-us/expert-centers/ | C38: P4 HCP list (ID/neurodevelopmental)
A39: ERN EpiCARE | B39: =HYPERLINK("https://epi-care.eu/","https://epi-care.eu/") -> https://epi-care.eu/ | C39: P4 secondary (rare/complex epilepsies); members list
A40: EC ERN Service Directory | B40: =HYPERLINK("https://webgate.ec.europa.eu/ernsd/","https://webgate.ec.europa.eu/ernsd/") -> https://webgate.ec.europa.eu/ernsd/ | C40: Official HCP lookup by ERN and country
A41: Orphanet — Angelman syndrome ORPHA:72 | B41: =HYPERLINK("https://www.orpha.net/en/disease/detail/72","https://www.orpha.net/en/disease/detail/72") -> https://www.orpha.net/en/disease/detail/72 | C41: Disease reference, expert centres, patient orgs (site uses bot check)
A42: Angelman e.V. (Germany) | B42: =HYPERLINK("https://angelman.de/","https://angelman.de/") -> https://angelman.de/ | C42: National patient org (founded 1993)
A43: AFSA — Association Française du Syndrome d'Angelman | B43: =HYPERLINK("https://www.angelman-afsa.org/","https://www.angelman-afsa.org/") -> https://www.angelman-afsa.org/ | C43: National patient org (France)
A44: OR.S.A. — Organizzazione Sindrome di Angelman (Italy) | B44: =HYPERLINK("https://sindromediangelman.org/","https://sindromediangelman.org/") -> https://sindromediangelman.org/ | C44: National patient org; REVEAL Italy communications; reference centres list
A45: Associazione Angelman / FROM — Registro Italiano Sindrome di Angelman (RISA) | B45: =HYPERLINK("https://www.associazioneangelman.it/","https://www.associazioneangelman.it/") -> https://www.associazioneangelman.it/ | C45: Italian national AS registry (FROM, Bergamo)
A46: ASA — Asociación Síndrome de Angelman (Spain) | B46: =HYPERLINK("https://angelman-asa.org/","https://angelman-asa.org/") -> https://angelman-asa.org/ | C46: National patient org (Spain)
A47: AngelmanUK | B47: =HYPERLINK("https://www.angelmanuk.org/","https://www.angelmanuk.org/") -> https://www.angelmanuk.org/ | C47: UK patient charity (no. 1197780)
A48: FAST UK — Foundation for Angelman Syndrome Therapeutics UK | B48: =HYPERLINK("https://cureangelman.org.uk/","https://cureangelman.org.uk/") -> https://cureangelman.org.uk/ | C48: UK research charity; trial news
A49: FAST (global) — drug development pipeline | B49: =HYPERLINK("https://cureangelman.org/current-pipeline","https://cureangelman.org/current-pipeline") -> https://cureangelman.org/current-pipeline | C49: Competitive pipeline overview
A50: Aspire NCT06617429 (Ultragenyx) location list via ICH GCP mirror | B50: =HYPERLINK("https://ichgcp.net/de/clinical-trials-registry/NCT06617429","https://ichgcp.net/de/clinical-trials-registry/NCT06617429") -> https://ichgcp.net/de/clinical-trials-registry/NCT06617429 | C50: German Aspire sites: UKE Hamburg, University of Leipzig, Haunersche Kinderklinik München
A51: Roche ForPatients — Aldebaran (alogabat) NCT05630066 | B51: =HYPERLINK("https://forpatients.roche.com/en/trials/neurodevelopmental-disorder/angelman-syndrome/study-to-investigate-the-pharmacokinetics-and-safety-an-84203.html","https://forpatients.roche.com/en/trials/neurodevelopmental-disorder/angelman-syndrome/study-to-investigate-the-pharmacokinetics-and-safety-an-84203.html") -> https://forpatients.roche.com/en/trials/neurodevelopmental-disorder/angelman-syndrome/study-to-investigate-the-pharmacokinetics-and-safety-an-84203.html | C51: Dr. von Haunersches Kinderspital München as a site (completed)
A52: Oak Hill Bio press release 28-Jul-2026 — BEACON (rugonersen) NCT07605429 | B52: =HYPERLINK("https://www.oakhillbio.com/news/oak-hill-bio-announces-dosing-of-first-participant-in-beacon-phase-3-clinical-trial-of-rugonersen-in-angelman-syndrome","https://www.oakhillbio.com/news/oak-hill-bio-announces-dosing-of-first-participant-in-beacon-phase-3-clinical-trial-of-rugonersen-in-angelman-syndrome") -> https://www.oakhillbio.com/news/oak-hill-bio-announces-dosing-of-first-participant-in-beacon-phase-3-clinical-trial-of-rugonersen-in-angelman-syndrome | C52: Rugonersen now Oak Hill Bio; Phase 3 BEACON started; US sites only as of Sep-2026
A53: LMU Klinikum — Angelman Zentrum München page | B53: =HYPERLINK("https://www.lmu-klinikum.de/ispz/schwerpunkte/kinderneurologie-und-entwicklungsneurologie/angelman-zentrum-munchen/92177eec075dcc14","https://www.lmu-klinikum.de/ispz/schwerpunkte/kinderneurologie-und-entwicklungsneurologie/angelman-zentrum-munchen/92177eec075dcc14") -> https://www.lmu-klinikum.de/ispz/schwerpunkte/kinderneurologie-und-entwicklungsneurologie/angelman-zentrum-munchen/92177eec075dcc14 | C53: AZM team (Makowski lead, Manssen), ASF/LADDER membership, links to Leipzig and Aachen
A54: Angelman e.V. — Angelman-Zentren page | B54: =HYPERLINK("https://angelman.de/hilfe-fuer-eltern/angelman-zentren/","https://angelman.de/hilfe-fuer-eltern/angelman-zentren/") -> https://angelman.de/hilfe-fuer-eltern/angelman-zentren/ | C54: The three German AS centres, named leads, Leipzig registry, Vogtareuth adult contact point, AZL B-centre of UZSEL
A55: Angelman e.V. medical-scientific advisory board flyer (hosted by UK Aachen) | B55: =HYPERLINK("https://www.ukaachen.de/fileadmin/files/zentren/mzeb/Angelman_Beiratsflyer.pdf","https://www.ukaachen.de/fileadmin/files/zentren/mzeb/Angelman_Beiratsflyer.pdf") -> https://www.ukaachen.de/fileadmin/files/zentren/mzeb/Angelman_Beiratsflyer.pdf | C55: Advisory board members (Makowski, Gburek-Augustat, Krey-Grauert, Maier, Hankowitz); AZM ran alogabat study; AZL in Phase 1/2 ASO trial and natural-history study
A56: Manssen L et al. Precision Medicine in Angelman Syndrome. Neuropediatrics 2025;56:69-82. doi:10.1055/a-2399-0191 | B56: =HYPERLINK("https://www.thieme-connect.com/products/ejournals/html/10.1055/a-2399-0191","https://www.thieme-connect.com/products/ejournals/html/10.1055/a-2399-0191") -> https://www.thieme-connect.com/products/ejournals/html/10.1055/a-2399-0191 | C56: Key German AS review; author/affiliation map for Munich + Leipzig; cites AWMF S1 PWS/AS diagnostic guideline (Buiting, Glaeser, Beygo 2020)
A57: Manssen L et al. Treatment responses to antiseizure medication in children with AS. Eur J Paediatr Neurol 2026;65:1-7. PMID 42771958 | B57: =HYPERLINK("https://pubmed.ncbi.nlm.nih.gov/42771958/","https://pubmed.ncbi.nlm.nih.gov/42771958/") -> https://pubmed.ncbi.nlm.nih.gov/42771958/ | C57: AZM natural-history cohort (n=101); authors incl. Borggraefe, Lemke, Krey, Gburek-Augustat, Nicolai
A58: Leipzig Angelman Syndrome Online Registry | B58: =HYPERLINK("https://www.uniklinikum-leipzig.de/einrichtungen/humangenetik/Seiten/de_Forschung-Fragebogen-Angelman-Syndrom.aspx","https://www.uniklinikum-leipzig.de/einrichtungen/humangenetik/Seiten/de_Forschung-Fragebogen-Angelman-Syndrom.aspx") -> https://www.uniklinikum-leipzig.de/einrichtungen/humangenetik/Seiten/de_Forschung-Fragebogen-Angelman-Syndrom.aspx | C58: National AS registry (P3 coordinator: Lemke, Krey); ethics 465/19-ek; co-funded by Angelman e.V.
A59: Beygo J et al. Update of the EMQN/ACGS best practice guidelines for molecular analysis of PWS and AS. Eur J Hum Genet 2019;27:1326-1340. PMID 31235867 | B59: =HYPERLINK("https://pubmed.ncbi.nlm.nih.gov/31235867/","https://pubmed.ncbi.nlm.nih.gov/31235867/") -> https://pubmed.ncbi.nlm.nih.gov/31235867/ | C59: International diagnostic guideline (Essen authors)
A60: se-atlas — ERN ITHACA German HCPs | B60: =HYPERLINK("https://www.se-atlas.de/map/ern/ERN%20ITHACA","https://www.se-atlas.de/map/ern/ERN%20ITHACA") -> https://www.se-atlas.de/map/ern/ERN%20ITHACA | C60: ITHACA HCPs: Düsseldorf, Erlangen, Essen, Göttingen, Hamburg (Human Genetics), Lübeck, Magdeburg, Münster, Tübingen
A61: ERN EpiCARE centre list | B61: =HYPERLINK("https://epi-care.eu/ern-epicare-centres/","https://epi-care.eu/ern-epicare-centres/") -> https://epi-care.eu/ern-epicare-centres/ | C61: German EpiCARE HCPs: Bonn, Erlangen, Freiburg, Tübingen
A62: se-atlas — German ZSE list | B62: =HYPERLINK("https://www.se-atlas.de/map/zse/","https://www.se-atlas.de/map/zse/") -> https://www.se-atlas.de/map/zse/ | C62: National ZSE network (P4 national analogue)
A63: Uniklinik RWTH Aachen — Angelman Zentrum Aachen / MZEB team | B63: =HYPERLINK("https://www.ukaachen.de/kliniken-institute/mzeb/fuer-patienten-und-zuweiser/angelman-zentrum-aachen/","https://www.ukaachen.de/kliniken-institute/mzeb/fuer-patienten-und-zuweiser/angelman-zentrum-aachen/") -> https://www.ukaachen.de/kliniken-institute/mzeb/fuer-patienten-und-zuweiser/angelman-zentrum-aachen/ | C63: Adult AS centre (founded 2021); Maier lead; Schulz MZEB head
A64: UKE — Arbeitsgruppe Neuropädiatrie | B64: =HYPERLINK("https://www.uke.de/kliniken-institute/kliniken/kinder-und-jugendmedizin/forschung/klinische-forschung/neurop%C3%A4diatrie.html","https://www.uke.de/kliniken-institute/kliniken/kinder-und-jugendmedizin/forschung/klinische-forschung/neurop%C3%A4diatrie.html") -> https://www.uke.de/kliniken-institute/kliniken/kinder-und-jugendmedizin/forschung/klinische-forschung/neurop%C3%A4diatrie.html | C64: Denecke (lead), Johannsen; 2025 publication list
A65: Duis J et al. Mol Genet Genomic Med 2022;10:e1843 (international AS standards of care) | B65: =HYPERLINK("https://pubmed.ncbi.nlm.nih.gov/35150089/","https://pubmed.ncbi.nlm.nih.gov/35150089/") -> https://pubmed.ncbi.nlm.nih.gov/35150089/ | C65: P1 international consensus — no German authors identified
A66: FAST news index (Aspire, CHAMPION, BEACON, alogabat updates) | B66: =HYPERLINK("https://cureangelman.org/news","https://cureangelman.org/news") -> https://cureangelman.org/news | C66: Competitive landscape timeline 2025–2026
A67: PNDS Syndrome d'Angelman — texte (HAS PDF) | B67: =HYPERLINK("https://www.has-sante.fr/upload/docs/application/pdf/2021-11/pnds_angelman_vf_.doc.pdf","https://www.has-sante.fr/upload/docs/application/pdf/2021-11/pnds_angelman_vf_.doc.pdf") -> https://www.has-sante.fr/upload/docs/application/pdf/2021-11/pnds_angelman_vf_.doc.pdf | C67: Coordinator Dr Delphine Héron; CRMR contacts; Annexe 1 participant list (p.61 — not extractable via tool)
A68: PNDS Angelman — argumentaire (HAS PDF) | B68: =HYPERLINK("https://www.has-sante.fr/upload/docs/application/pdf/2021-11/argumentaire_pnds_angelman_vf.pdf","https://www.has-sante.fr/upload/docs/application/pdf/2021-11/argumentaire_pnds_angelman_vf.pdf") -> https://www.has-sante.fr/upload/docs/application/pdf/2021-11/argumentaire_pnds_angelman_vf.pdf | C68: Method, literature base (249 studies), coordination by Dr Héron
A69: Duis J et al. Mol Genet Genomic Med 2022;10(3):e1843 (PMID 35150089) | B69: =HYPERLINK("https://doi.org/10.1002/mgg3.1843","https://doi.org/10.1002/mgg3.1843") -> https://doi.org/10.1002/mgg3.1843 | C69: International AS standards of care (no French authors identified)
A70: AFSA — Conseil Médical et Scientifique (2026) | B70: =HYPERLINK("https://www.angelman-afsa.org/afsa/son-equipe/conseil-medical-et-scientifique/afsa/son-equipe/conseil-medical-et-scientifique/le-conseil-medical-et-scientifique","https://www.angelman-afsa.org/afsa/son-equipe/conseil-medical-et-scientifique/afsa/son-equipe/conseil-medical-et-scientifique/le-conseil-medical-et-scientifique") -> https://www.angelman-afsa.org/afsa/son-equipe/conseil-medical-et-scientifique/afsa/son-equipe/conseil-medical-et-scientifique/le-conseil-medical-et-scientifique | C70: Current AS-engaged clinician roster (Desnous, Hully, Chaumette, Héron, Charles, Consoli, Riccardi)
A71: AFSA — Nouvelle présidence au CMS | B71: =HYPERLINK("https://www.angelman-afsa.org/afsa/son-equipe/conseil-medical-et-scientifique/nouvelle-presidence-du-cms","https://www.angelman-afsa.org/afsa/son-equipe/conseil-medical-et-scientifique/nouvelle-presidence-du-cms") -> https://www.angelman-afsa.org/afsa/son-equipe/conseil-medical-et-scientifique/nouvelle-presidence-du-cms | C71: Hully succeeded Peudenier; Hully Necker CRMR DI & SFNP roles
A72: AFSA livret — contributeurs | B72: =HYPERLINK("https://www.livret-angelman-afsa.org/les-contributeurs","https://www.livret-angelman-afsa.org/les-contributeurs") -> https://www.livret-angelman-afsa.org/les-contributeurs | C72: Historic AFSA CMS (Dorison, Livet, Moncla, Peudenier, Héron)
A73: AFSA Rapport d'activités 2021 | B73: =HYPERLINK("https://www.angelman-afsa.org/fichiers/Rapport%20d'Activites%202021-1654173306.pdf","https://www.angelman-afsa.org/fichiers/Rapport%20d'Activites%202021-1654173306.pdf") -> https://www.angelman-afsa.org/fichiers/Rapport%20d'Activites%202021-1654173306.pdf | C73: CMS finalised PNDS; AFSA–FAST France–Syndrome Angelman France clinical-research working group
A74: ERN ITHACA — Paris centre (AP-HP consortium) | B74: =HYPERLINK("https://ern-ithaca.eu/about-us/expert-centers/ern-ithaca-paris-center-robert-debre-university-hospital/","https://ern-ithaca.eu/about-us/expert-centers/ern-ithaca-paris-center-robert-debre-university-hospital/") -> https://ern-ithaca.eu/about-us/expert-centers/ern-ithaca-paris-center-robert-debre-university-hospital/ | C74: P4: Verloes (EU coordinator), Héron, Bahi-Buisson, Rio, Valence, Germanaud, Amiel, Lehalle
A75: ERN ITHACA — Who we are | B75: =HYPERLINK("https://ern-ithaca.eu/about-us/who-we-are/","https://ern-ithaca.eu/about-us/who-we-are/") -> https://ern-ithaca.eu/about-us/who-we-are/ | C75: Coordination at AP-HP since 2018 (Verloes)
A76: ERN ITHACA — Lyon centre | B76: =HYPERLINK("https://ern-ithaca.eu/about-us/expert-centers/ern-ithaca-lyon-center/","https://ern-ithaca.eu/about-us/expert-centers/ern-ithaca-lyon-center/") -> https://ern-ithaca.eu/about-us/expert-centers/ern-ithaca-lyon-center/ | C76: P4: HCL Lyon (Rossi); CLAD Sud-Est sites
A77: ERN ITHACA — Dijon centre | B77: =HYPERLINK("https://ern-ithaca.eu/about-us/expert-centers/ern-ithaca-dijon-center/","https://ern-ithaca.eu/about-us/expert-centers/ern-ithaca-dijon-center/") -> https://ern-ithaca.eu/about-us/expert-centers/ern-ithaca-dijon-center/ | C77: P4: CHU Dijon (Faivre)
A78: EpiCARE — Necker-Enfants Malades | B78: =HYPERLINK("https://epi-care.eu/hospitals/necker-enfants-malades-aphp/","https://epi-care.eu/hospitals/necker-enfants-malades-aphp/") -> https://epi-care.eu/hospitals/necker-enfants-malades-aphp/ | C78: P4 EpiCARE full member; HCP coordinator Nabbout
A79: Necker CRéER rare epilepsies | B79: =HYPERLINK("https://maladiesrares-necker.aphp.fr/rare-epilepsies/","https://maladiesrares-necker.aphp.fr/rare-epilepsies/") -> https://maladiesrares-necker.aphp.fr/rare-epilepsies/ | C79: AS in rare-epilepsy scope; Timone = CRéER coordinating centre
A80: Institut Imagine — Rima Nabbout | B80: =HYPERLINK("https://www.institutimagine.org/en/users/rimanabboutaphpfr","https://www.institutimagine.org/en/users/rimanabboutaphpfr") -> https://www.institutimagine.org/en/users/rimanabboutaphpfr | C80: BNDMR scientific-committee chair; trial PI roles
A81: ESCO/STXBP1 France page | B81: =HYPERLINK("https://stxbp1eu.org/france/","https://stxbp1eu.org/france/") -> https://stxbp1eu.org/france/ | C81: Milh and Desnous roles at Timone
A82: NovaPharma EU news (Aspire) | B82: =HYPERLINK("https://novapharmanews.com/eu/news/apazunersen-aspire-angelman-misses-endpoints","https://novapharmanews.com/eu/news/apazunersen-aspire-angelman-misses-endpoints") -> https://novapharmanews.com/eu/news/apazunersen-aspire-angelman-misses-endpoints | C82: Aspire EU sites in Germany, Poland, Spain (secondary source)
A83: Husson T et al. Eur J Hum Genet 2024 (PMID 37872275) | B83: =HYPERLINK("https://pubmed.ncbi.nlm.nih.gov/37872275/","https://pubmed.ncbi.nlm.nih.gov/37872275/") -> https://pubmed.ncbi.nlm.nih.gov/37872275/ | C83: French NDD genetics network affiliations (Pitié CRMR DI, Dijon, Lille, Toulouse)
A84: AP-HP registre — ION582-CS1 (HALOS) | B84: =HYPERLINK("https://www.aphp.fr/registre-des-essais-cliniques/etude-visant-evaluer-la-securite-la-tolerance-la-pharmacocinetique-et","https://www.aphp.fr/registre-des-essais-cliniques/etude-visant-evaluer-la-securite-la-tolerance-la-pharmacocinetique-et") -> https://www.aphp.fr/registre-des-essais-cliniques/etude-visant-evaluer-la-securite-la-tolerance-la-pharmacocinetique-et | C84: Coordinating investigator Bahi-Buisson; Necker coordinating centre; closed to inclusion
A85: Eichor mirror of CT.gov NCT05127226 (HALOS) | B85: =HYPERLINK("https://eichor.com/study/NCT05127226","https://eichor.com/study/NCT05127226") -> https://eichor.com/study/NCT05127226 | C85: 11 locations incl. Necker-Enfants Malades, Paris
A86: FAST France — Ionis page | B86: =HYPERLINK("https://www.fastfrance.org/dossier-angelman/ionis-syndrome-dangelman/","https://www.fastfrance.org/dossier-angelman/ionis-syndrome-dangelman/") -> https://www.fastfrance.org/dossier-angelman/ionis-syndrome-dangelman/ | C86: Necker HALOS centre opened June 2023
A87: AP-HP registre — GTX-102 Ph2 basket (CL210) | B87: =HYPERLINK("https://www.aphp.fr/registre-des-essais-cliniques/etude-en-ouvert-de-phase-2-de-type-panier-visant-evaluer-linnocuite","https://www.aphp.fr/registre-des-essais-cliniques/etude-en-ouvert-de-phase-2-de-type-panier-visant-evaluer-linnocuite") -> https://www.aphp.fr/registre-des-essais-cliniques/etude-en-ouvert-de-phase-2-de-type-panier-visant-evaluer-linnocuite | C87: Coordinating investigator Bahi-Buisson, Necker
A88: AP-HP registre — GTX-102 LTE (CL302) | B88: =HYPERLINK("https://hopital-broca.aphp.fr/registre-des-essais-cliniques/etude-dextension-long-terme-portant-sur-la-securite-demploi-et-65","https://hopital-broca.aphp.fr/registre-des-essais-cliniques/etude-dextension-long-terme-portant-sur-la-securite-demploi-et-65") -> https://hopital-broca.aphp.fr/registre-des-essais-cliniques/etude-dextension-long-terme-portant-sur-la-securite-demploi-et-65 | C88: Coordinating investigator Milh (AP-HM); recruiting at Necker
A89: Duis J et al. Consensus standards of care for AS. Mol Genet Genomic Med 2022;10:e1843 (PMID 35150089) | B89: =HYPERLINK("https://onlinelibrary.wiley.com/doi/epdf/10.1002/mgg3.1843","https://onlinelibrary.wiley.com/doi/epdf/10.1002/mgg3.1843") -> https://onlinelibrary.wiley.com/doi/epdf/10.1002/mgg3.1843 | C89: P1 international consensus — no Italian authors
A90: OR.S.A. – Centri di riferimento (AS reference centre list) | B90: =HYPERLINK("https://sindromediangelman.org/centri-sintrome-di-angelman/","https://sindromediangelman.org/centri-sintrome-di-angelman/") -> https://sindromediangelman.org/centri-sintrome-di-angelman/ | C90: P5 national AS reference centres + named clinicians
A91: OR.S.A. – Percorsi Diagnostici Assistenziali | B91: =HYPERLINK("https://sindromediangelman.org/percorsi-diagnostici-sindrome-di-angelman/","https://sindromediangelman.org/percorsi-diagnostici-sindrome-di-angelman/") -> https://sindromediangelman.org/percorsi-diagnostici-sindrome-di-angelman/ | C91: Patient-org diagnostic pathway (not a clinical guideline; no named author cohort)
A92: ClinicalTrials.gov NCT06914609 (REVEAL) – mirror ICH GCP | B92: =HYPERLINK("https://ichgcp.net/clinical-trials-registry/NCT06914609","https://ichgcp.net/clinical-trials-registry/NCT06914609") -> https://ichgcp.net/clinical-trials-registry/NCT06914609 | C92: REVEAL site list incl. 4 Italian sites (Medea not yet recruiting); EU CT 2024-519711-33-00
A93: ClinicalTrials.gov NCT05127226 (HALOS) – mirror ICH GCP | B93: =HYPERLINK("https://ichgcp.net/clinical-trials-registry/NCT05127226","https://ichgcp.net/clinical-trials-registry/NCT05127226") -> https://ichgcp.net/clinical-trials-registry/NCT05127226 | C93: HALOS site list – Italy: AOU Pisana only
A94: ClinicalTrials.gov NCT06617429 (Aspire) – mirror ICH GCP | B94: =HYPERLINK("https://ichgcp.net/clinical-trials-registry/NCT06617429","https://ichgcp.net/clinical-trials-registry/NCT06617429") -> https://ichgcp.net/clinical-trials-registry/NCT06617429 | C94: Aspire sites – no Italian site
A95: ClinicalTrials.gov NCT07157254 (Aurora, GTX-102 Ph2) – mirror ICH GCP | B95: =HYPERLINK("https://ichgcp.net/clinical-trials-registry/NCT07157254","https://ichgcp.net/clinical-trials-registry/NCT07157254") -> https://ichgcp.net/clinical-trials-registry/NCT07157254 | C95: Italian Aurora sites: Meyer, Besta, Rome
A96: OR.S.A. letter on Aurora (16-Jan-2026) | B96: =HYPERLINK("https://sindromediangelman.org/wp-content/uploads/2026/01/Aggiornamento-Trial-Ultragenix.pdf","https://sindromediangelman.org/wp-content/uploads/2026/01/Aggiornamento-Trial-Ultragenix.pdf") -> https://sindromediangelman.org/wp-content/uploads/2026/01/Aggiornamento-Trial-Ultragenix.pdf | C96: Named Aurora leads: D'Arrigo, Guerrini, D.I. Battaglia (Gemelli)
A97: CTIS 2024-519393-39-00 (Aurora) | B97: =HYPERLINK("https://ctis.eu/trial/2024-519393-39-00","https://ctis.eu/trial/2024-519393-39-00") -> https://ctis.eu/trial/2024-519393-39-00 | C97: EU Aurora registration; 3 EU countries, 8 sites
A98: Portale Malattie Rare – ERN Italian members | B98: =HYPERLINK("https://www.malattierare.gov.it/ern/ricerca","https://www.malattierare.gov.it/ern/ricerca") -> https://www.malattierare.gov.it/ern/ricerca | C98: P4 ERN ITHACA and EpiCARE Italian full-member lists
A99: ePAG Italia – ERN EpiCARE | B99: =HYPERLINK("https://www.epag-italia.it/it/ern/ern-epicare","https://www.epag-italia.it/it/ern/ern-epicare") -> https://www.epag-italia.it/it/ern/ern-epicare | C99: EpiCARE Italian centres and named representatives (Nobili, Darra)
A100: Portale Malattie Rare – centres for Angelman syndrome (68) | B100: =HYPERLINK("https://www.malattierare.gov.it/centri_cura/elenco_per_malattia/130","https://www.malattierare.gov.it/centri_cura/elenco_per_malattia/130") -> https://www.malattierare.gov.it/centri_cura/elenco_per_malattia/130 | C100: Regional rare-disease network presidi certified for AS
...

Sheet Verification_Flags
A1: Verification_Flags — adversarial QA pass (affiliation currency, independence/compliance, provenance, wording/counts, drug premise). Red cells on home sheets = flagged, not corrected.
A2: # | B2: Sheet | C2: Cell(s) | D2: Item | E2: Finding | F2: Recommended correction | G2: Verdict
A3: 1 | B3: Country_Centres | C3: F20 | D3: [Germany] LMU Klinikum München — field: KOL / REVEAL PI | E3: ClinicalTrials.gov and the Ionis letter name the institution only; the REVEAL site PI is not public. Makowski leads the AZM but is not confirmed as PI. Borggräfe is section head. No public evidence links Prof. Angela Abicht to AS (name suggested in the brief), so she was not included. | F3: Confirm site PI and sub-investigators with Ionis Clinical Operations / CTIS Part I site list before outreach | G3: PART-UNVERIFIABLE
A4: 2 | B4: Country_Centres | C4: B20; H20; K20; B21; H21; K21 | D4: [Germany] LMU Klinikum München; Universitätsklinikum Leipzig — field: Tier / P1 / P4 | E4: Tier 1 depends on national-analogue pillars (P1 = Angelman e.V. advisory board; P4 = ASF-recognised clinic / ZSE B-centre). Neither centre is on se-atlas ERN ITHACA/EpiCARE lists, and no German author is on the 2022 international consensus. | F4: Accept the analogue reading (as the brief allows for Germany) or downgrade both to Tier 2 under an ERN-only P4 reading | G4: WORDING
A5: 3 | B5: Country_Centres | C5: B22 | D5: [Germany] Universitätsklinikum Essen — field: Tier | E5: Formally meets Tier 1 (diagnostic guideline authors + ITHACA + AS molecular publications), but it is a lab-genetics institute without an AS treatment service. KOLs are PhD scientists. | F5: Keep Tier 1 for evidence/diagnostics; exclude from site-readiness shortlists | G5: WORDING
A6: 4 | B6: KOL_Roster | C6: C39 | D6: [Germany] Prof. Dr. Karin Buiting — field: Affiliation | E6: She does not appear as a current contact on the Essen imprinting page (Beygo, Kanber, Ueberberg listed); she may be retired or emerita. | F6: Verify current status before listing as an active KOL | G6: OUTDATED
A7: 5 | B7: Country_Centres | C7: F23 | D7: [Germany] UKE Hamburg — field: KOL | E7: UKE is a GTX-102 Ph1/2 and Aspire site, but no investigator is publicly named. Denecke and Johannsen are gap-filled from the department directory. | F7: Verify Aspire site PI via Ultragenyx or CTIS | G7: PART-UNVERIFIABLE
A8: 6 | B8: Country_Centres | C8: I20; J20; I21; J21; I23; J23 | D8: [Germany] Leipzig; LMU; UKE (Aspire sites) — field: P2/P3 competitor | E8: Aspire (apazunersen) missed its primary and key secondary endpoints on 2-Sep-2026. Ultragenyx is reviewing the programme, and the Aurora study (NCT07157254) status is unclear. | F8: Treat German Aspire sites as experienced, potentially displaceable intrathecal-ASO sites; avoid competitor-disparaging messaging | G8: DRUG-PREMISE
A9: 7 | B9: KOL_Roster | C9: Sources_Caveats!B195; Sources_Caveats!C195 | D9: [Germany] Competitor landscape (rugonersen) — field: P2 competitor | E9: Rugonersen is no longer a Roche asset: Oak Hill Bio is running Phase 3 BEACON (NCT07605429; first dosed Jul-2026; US sites only as of Sep-2026). This contradicts the brief's 'TANGELO discontinued/verify' framing. | F9: Update the competitor list: rugonersen (Oak Hill Bio) Phase 3 BEACON active; watch for German site activation | G9: CONTRADICTED
A10: 8 | B10: Country_Centres | C10: M20 | D10: [Germany] REVEAL premise — field: Notes | E10: Verified: Cohort 1 = 136 enrolled (Ionis 6-Jul-2026); CT.gov actual enrolment 156; protocol amended Dec-2025 to two arms (80 mg vs placebo); EU uses a skin-prick sham; CTIS 2024-519711-33-00 (an aggregator lists transition number -01). | F10: None — note the CTIS suffix variant | G10: VERIFIED
A11: 9 | B11: KOL_Roster | C11: B35 | D11: [Germany] Dr. Ilona Krey — field: Name | E11: She appears as 'Ilona Krey' on publications and the registry, and as 'Ilona Krey-Grauert' on the Angelman e.V. advisory-board flyer. | F11: Use 'Dr. med. Ilona Krey (Krey-Grauert)' in CRM to avoid duplicate records | G11: WORDING
A12: 10 | B12: KOL_Roster | C12: L36; P36; L23; P23 | D12: [Germany] Prof. Dr. Johannes R. Lemke; Prof. Dr. Ingo Borggräfe — field: Scores | E12: Scores use the evidence floor (only AS papers fetched). Both are prolific in epilepsy genetics/epileptology, so publication and speaker scores are likely understated. | F12: Re-score after a full PubMed / congress-faculty check | G12: PART-UNVERIFIABLE
A13: 11 | B13: KOL_Roster | C13: D22 | D13: [Germany] Dr. Christine Makowski — field: Compliance | E13: No Ionis/Ultragenyx/Roche consultancy disclosure found. Her 2024 congress abstract states no conflict of interest. The AZM ran the Roche alogabat study (investigator role, not employment). A non-clinical advisory-board member (Dr. Johannes Hankowitz, AMNOG consultant) is not listed as a KOL. | F13: Run a standard transparency (FSA/EFPIA ToV) check before contracting | G13: VERIFIED
A14: 12 | B14: Country_Centres | C14: J20:J36 | D14: [Germany] HALOS NCT05127226 — field: P3 | E14: HALOS lists 5 non-US sites, but no German site was identified (the CT.gov page did not render in this pass). | F14: Confirm that no German HALOS site exists | G14: PART-UNVERIFIABLE
... A94: 92 | B94: README / Infrastructure (drug premise) | C94: n/a — no cell states this figure in the workbook | D94: [Asset] AS prevalence wording | E94: Ionis cites 1 in 21,000; Duis 2022 ~1/12,000; Danish birth incidence 1:24,580 (Mertz 2013). | F94: Quote range 1:12,000–1:24,000 with sources. | G94: WORDING
A96: ="Closing note — checked and passed: "&COUNTIF(G3:G94,"VERIFIED")&_xlfn._LONGTEXT(" items VERIFIED (trial identifiers, REVEAL dose/arms/endpoint/topline timing, EU sham control, first EU sites, UK enrolment, orphan designations, ERN membership checks for Spain, no Spanish P1 author, HALOS/Aspire site attributions, and independence scree","ns: no KOL found to be an Ionis/Ultragenyx/Roche/Ovid/Neuren employee). The remaining ")&COUNTIF(G3:G94,"<>VERIFIED")&" flags ("&COUNTIF(G3:G94,"PART-UNVERIFIABLE")&" PART-UNVERIFIABLE, "&COUNTIF(G3:G94,"OUTDATED")&" OUTDATED, "&COUNTIF(G3:G94,"WORDING")&" WORDING, "&COUNTIF(G3:G94,"CONTRADICTED")&" CONTRADICTED, "&COUNTIF(G3:G94,"DRUG-PREMISE")&" DRUG-PREMISE) require your decision; their source cells are highlighted red on the home sheets and nothing has been auto-corrected." -> Closing note — checked and passed: 27 items VERIFIED (trial identifiers, REVEAL dose/arms/endpoint/topline timing, EU sham control, first EU sites, UK enrolment, orphan designations, ERN membership checks for Spain, no Spanish P1 author, HALOS/Aspire site attributions, and independence screens: no KOL found to be an Ionis/Ultragenyx/Roche/Ovid/Neuren employee). The remaining 65 flags (33 PART-UNVERIFIABLE, 9 OUTDATED, 16 WORDING, 3 CONTRADICTED, 4 DRUG-PREMISE) require your decision; their source cells are highlighted red on the home sheets and nothing has been auto-corrected.
